Lab09/NextPClogic.v
`timescale 1ns / 1ps
module NextPClogic(NextPC, CurrentPC, SignExtImm64, Branch, ALUZero, Uncondbranch); 
   input [63:0] CurrentPC, SignExtImm64; 
   input 	Branch, ALUZero, Uncondbranch; 
   output reg [63:0] NextPC; 
   wire [63:0] Tmpimm;
	assign Tmpimm = SignExtImm64 << 2;
   always @(*)
		begin
		if(Uncondbranch) begin
			NextPC <= CurrentPC + Tmpimm;
		end else if (Branch) begin
			if (ALUZero) begin
				NextPC <= CurrentPC + Tmpimm;
			end else begin
				NextPC <= CurrentPC + 4;
			end
		end else begin
			NextPC <= CurrentPC + 4;
		end
	end

endmodule

Lab09/DataMemory.v
`timescale 1ns / 1ps

`define SIZE 1024

module DataMemory(ReadData , Address , WriteData , MemoryRead , MemoryWrite , Clock);
   input [63:0]      WriteData;
   input [63:0]      Address;
   input             Clock, MemoryRead, MemoryWrite;
   output reg [63:0] ReadData;

   reg [7:0] 	     memBank [`SIZE-1:0];


   // This task is used to write arbitrary data to the Data Memory by
   // the intialization block.
   task initset;
      input [63:0] addr;
      input [63:0] data;
      begin
	 memBank[addr] =  data[63:56] ; // Big-endian for the win...
	 memBank[addr+1] =  data[55:48];
	 memBank[addr+2] =  data[47:40];
	 memBank[addr+3] =  data[39:32];
	 memBank[addr+4] =  data[31:24];
	 memBank[addr+5] =  data[23:16];
	 memBank[addr+6] =  data[15:8];
	 memBank[addr+7] =  data[7:0];
      end
   endtask


   initial
     begin
        // preseting some data in the data memory used by test #1

        // Address 0x0 gets 0x1
        initset( 64'h0,  64'h1);  //Counter variable
        initset( 64'h8,  64'ha);  //Part of mask
        initset( 64'h10, 64'h5);  //Other part of mask
        initset( 64'h18, 64'h0ffbea7deadbeeff); //big constant
        initset( 64'h20, 64'h0); //clearing space

        // Add any data you need for your tests here.

     end

   // This always block reads the data memory and places a double word
   // on the ReadData bus.
   always @(posedge Clock)
     begin
        if(MemoryRead)
          begin
             ReadData[63:56] <=  memBank[Address];
             ReadData[55:48] <=  memBank[Address+1];
             ReadData[47:40] <=  memBank[Address+2];
             ReadData[39:32] <=  memBank[Address+3];
             ReadData[31:24] <=  memBank[Address+4];
             ReadData[23:16] <=  memBank[Address+5];
             ReadData[15:8] <=  memBank[Address+6];
             ReadData[7:0] <=  memBank[Address+7];
          end
     end

   // This always block takes data from the WriteData bus and writes
   // it into the DataMemory.
   always @(posedge Clock)
     begin
        if(MemoryWrite)
          begin
             memBank[Address] <= #3 WriteData[63:56] ;
             memBank[Address+1] <= #3 WriteData[55:48];
             memBank[Address+2] <= #3 WriteData[47:40];
             memBank[Address+3] <= #3 WriteData[39:32];
             memBank[Address+4] <= #3 WriteData[31:24];
             memBank[Address+5] <= #3 WriteData[23:16];
             memBank[Address+6] <= #3 WriteData[15:8];
             memBank[Address+7] <= #3 WriteData[7:0];
             // Could be useful for debugging:
             // $display("Writing Address:%h Data:%h",Address, WriteData);
          end
     end
     //$display("Dmem:%h",ReadData);
endmodule

Lab09/SignExtender.v
module SignExtender(BusImm, Imm26, Ctrl); 
   output reg [63:0] BusImm; 
   input [25:0]  Imm26;
   input [1:0]	Ctrl; 
   
   reg extBit; 
   always @(Ctrl, Imm26)
   begin
		case(Ctrl)
			2'b00: /* I-Type instructions */
				begin
				extBit = 0;
			    BusImm = {{52{extBit}}, Imm26[21:10]};
			    end
			2'b01: /* D-Type instructions */
				begin
				extBit = Imm26[20];
				BusImm = {{55{extBit}}, Imm26[20:12]};
				end
			2'b10: /* B instructions */
				begin
				extBit = Imm26[25];
				BusImm = {{38{extBit}}, Imm26[25:0]};
				end
			2'b11: /* CBZ instructions */
				begin
				extBit = Imm26[23]; 
				BusImm = {{45{extBit}}, Imm26[23:5]};
				end
		endcase
	end
endmodule

Lab09/RegisterFile.v


module RegisterFile(BusA, BusB, BusW, RA, RB, RW, RegWr, Clk);
    output [63:0] BusA;
    output [63:0] BusB;
    input [63:0] BusW;
    input [4:0] RW;
    input [4:0] RA;
    input [4:0] RB;
    input RegWr;
    input Clk;
    reg [63:0] registers [31:0];
	
	
	assign #2 BusA = (RA==31) ? 0 : registers[RA];
	assign #2 BusB = (RB==31) ? 0 : registers[RB];
     
    always @ (negedge Clk) begin
        if(RegWr && (RW != 31))
            registers[RW] <= #3 BusW;
            registers[31] <= #3 0; 
        $display("Ra:%d", RA);    
        $display("Rb:%d", RB);
        $display("Rw:%d", RW);
        $display("BusA:%h", BusA);
        $display("BusB:%h", BusB);
        $display("BusW:%h", BusW);
    end
    
    
	

    

endmodule

Lab09/ALU.v
`define AND   4'b0000
`define OR    4'b0001
`define ADD   4'b0010
`define SUB   4'b0110
`define PassB 4'b0111

module ALU(BusW, BusA, BusB, ALUCtrl, Zero);
    
    output  [63:0] BusW;
    input   [63:0] BusA, BusB;
    input   [3:0] ALUCtrl;
    output  Zero;
    
    reg     [63:0] BusW;
    
    always @(ALUCtrl or BusA or BusB) begin
        case(ALUCtrl)
            4'b0000: begin /* AND */
                BusW = BusA & BusB;
            end
            4'b0001: begin /* OR */
				BusW = BusA | BusB;
			end
			4'b0010: begin /*ADD */
				BusW = BusA + BusB;
			end
			4'b0110: begin /* SUB */
				BusW = BusA - BusB;
			end
			4'b0111: begin /*PassB */
				BusW = BusB;
			end
			
        endcase
        $display("ALUOUT:%h", BusW);
    end
	
    assign Zero = (BusW ? 0 : 1);
endmodule

Lab09/SingleCycleControl.v
`define OPCODE_ANDREG 11'b?0001010???
`define OPCODE_ORRREG 11'b?0101010???
`define OPCODE_ADDREG 11'b?0?01011???
`define OPCODE_SUBREG 11'b?1?01011???

`define OPCODE_ADDIMM 11'b?0?10001???
`define OPCODE_SUBIMM 11'b?1?10001???

`define OPCODE_MOVZ   11'b110100101??

`define OPCODE_B      11'b?00101?????
`define OPCODE_CBZ    11'b?011010????

`define OPCODE_LDUR   11'b11111000010
`define OPCODE_STUR   11'b??111000000
`timescale 1ns / 1ps
module control(
    output reg reg2loc,
    output reg alusrc,
    output reg mem2reg,
    output reg regwrite,
    output reg memread,
    output reg memwrite,
    output reg branch,
    output reg uncond_branch,
    output reg [3:0] aluop,
    output reg [1:0] signop,
    input [10:0] opcode
);

always @(*)
begin
    casez (opcode)
    
    `OPCODE_ANDREG : 
	begin // AND
	    reg2loc       <= 1'b0;
            alusrc        <= 1'b0;
            mem2reg       <= 1'b0;
            regwrite      <= 1'b1;
            memread       <= 1'b0;
            memwrite      <= 1'b0;
            branch        <= 1'b0;
            uncond_branch <= 1'b0;
            aluop         <= 4'b0000;
            signop        <= 2'bxx;
	end
		
    `OPCODE_ORRREG : // ORR
	begin
	    reg2loc       <= 1'b0;
            alusrc        <= 1'b0;
            mem2reg       <= 1'b0;
            regwrite      <= 1'b1;
            memread       <= 1'b0;
            memwrite      <= 1'b0;
            branch        <= 1'b0;
            uncond_branch <= 1'b0;
            aluop         <= 4'b0001;
            signop        <= 2'bxx;
	end
		
    `OPCODE_ADDREG : // ADDR
	begin
	    reg2loc       <= 1'b0;
            alusrc        <= 1'b0;
            mem2reg       <= 1'b0;
            regwrite      <= 1'b1;
            memread       <= 1'b0;
            memwrite      <= 1'b0;
            branch        <= 1'b0;
            uncond_branch <= 1'b0;
            aluop         <= 4'b0010;
            signop        <= 2'bxx;
	end
		
    `OPCODE_SUBREG : // SUBR
	begin
	    reg2loc       <= 1'b0;
            alusrc        <= 1'b0;
            mem2reg       <= 1'b0;
            regwrite      <= 1'b1;
            memread       <= 1'b0;
            memwrite      <= 1'b0;
            branch        <= 1'b0;
            uncond_branch <= 1'b0;
            aluop         <= 4'b0110;
            signop        <= 2'bxx;
        end
		
    `OPCODE_ADDIMM : // ADDI			
	begin
		    reg2loc       <= 1'bx;
            alusrc        <= 1'b1;
            mem2reg       <= 1'b0;
            regwrite      <= 1'b1;
            memread       <= 1'b0;
            memwrite      <= 1'b0;
            branch        <= 1'b0;
            uncond_branch <= 1'b0;
            aluop         <= 4'b0010;
            signop        <= 2'b00;
		end
		
    `OPCODE_SUBIMM : // SUBI			
	begin
	    reg2loc       <= 1'bx;
            alusrc        <= 1'b1;
            mem2reg       <= 1'b0;
            regwrite      <= 1'b1;
            memread       <= 1'b0;
            memwrite      <= 1'b0;
            branch        <= 1'b0;
            uncond_branch <= 1'b0;
            aluop         <= 4'b0110;
            signop        <= 2'b00;
	end
		
		
    `OPCODE_B : // B
	begin
	    reg2loc       <= 1'bx;
            alusrc        <= 1'b0;
            mem2reg       <= 1'bx;
            regwrite      <= 1'b0;
            memread       <= 1'b0;
            memwrite      <= 1'b0;
            branch        <= 1'b0;
            uncond_branch <= 1'b1;
            aluop         <= 4'b0111;
            signop        <= 2'b10;
	end
		
    `OPCODE_CBZ : // CBZ
	begin
	    reg2loc       <= 1'b1;
            alusrc        <= 1'b0;
            mem2reg       <= 1'bx;
            regwrite      <= 1'b0;
            memread       <= 1'b0;
            memwrite      <= 1'b0;
            branch        <= 1'b1;
            uncond_branch <= 1'b0;
            aluop         <= 4'b0111;
            signop        <= 2'b11;
	end
		
    `OPCODE_LDUR : // LDUR
	  begin
	    reg2loc       <= 1'bx;
            alusrc        <= 1'b1;
            mem2reg       <= 1'b1;
            regwrite      <= 1'b1;
            memread       <= 1'b1;
            memwrite      <= 1'b0;
            branch        <= 1'b0;
            uncond_branch <= 1'bx;
            aluop         <= 4'b0010;
            signop        <= 2'b01;
	  end
		
    `OPCODE_STUR : //STUR
	  begin
	    reg2loc       <= 1'b1;
            alusrc        <= 1'b1;
            mem2reg       <= 1'bx;
            regwrite      <= 1'b0;
            memread       <= 1'b0;
            memwrite      <= 1'b1;
            branch        <= 1'b0;
            uncond_branch <= 1'b0;
            aluop         <= 4'b0010;
            signop        <= 2'b01;
	  end

        default:
        begin
            reg2loc       <= 1'bx;
            alusrc        <= 1'bx;
            mem2reg       <= 1'bx;
            regwrite      <= 1'b0;
            memread       <= 1'b0;
            memwrite      <= 1'b0;
            branch        <= 1'b0;
            uncond_branch <= 1'b0;
            aluop         <= 4'bxxxx;
            signop        <= 2'bxx;
        end
        
    endcase
    
    //$display("mem2reg:%h", mem2reg);
    //$display("reg2loc:%h", reg2loc);
    //$display("regwrite:%h", regwrite);
    //$display("memread:%h", memread);
    //$display("memwrite:%h", memwrite);
    //$display("branch:%h", branch);
    //$display("uncond_branch:%h", uncond_branch);
    //$display("aluop:%h", aluop);
    //$display("signop:%h", signop);
    

end

endmodule

Lab09/InstructionMemory.v
`timescale 1ns / 1ps
/*
 * Module: InstructionMemory
 *
 * Implements read-only instruction memory
 * 
 */
module InstructionMemory (
    Data,
    Address
);
  parameter T_rd = 20;
  parameter MemSize = 40;

  output [31:0] Data;
  input [63:0] Address;
  reg [31:0] Data;

  /*
    * ECEN 350 Processor Test Functions
    * Texas A&M University
    */

  always @(Address) begin

    case (Address)

      /* Test Program 1:
	 * Program loads constants from the data memory. Uses these constants to test
	 * the following instructions: LDUR, ORR, AND, CBZ, ADD, SUB, STUR and B.
	 * 
	 * Assembly code for test:
	 * 
	 * 0: LDUR X9, [XZR, 0x0]    //Load 1 into x9
	 * 4: LDUR X10, [XZR, 0x8]   //Load a into x10
	 * 8: LDUR X11, [XZR, 0x10]  //Load 5 into x11
	 * C: LDUR X12, [XZR, 0x18]  //Load big constant into x12
	 * 10: LDUR X13, [XZR, 0x20]  //load a 0 into X13
	 * 
	 * 14: ORR X10, X10, X11  //Create mask of 0xf
	 * 18: AND X12, X12, X10  //Mask off low order bits of big constant
	 * 
	 * loop:
	 * 1C: CBZ X12, end  //while X12 is not 0
	 * 20: ADD X13, X13, X9  //Increment counter in X13
	 * 24: SUB X12, X12, X9  //Decrement remainder of big constant in X12
	 * 28: B loop  //Repeat till X12 is 0
	 * 2C: STUR X13, [XZR, 0x20]  //store back the counter value into the memory location 0x20
	 */


      63'h000: Data = 32'hF84003E9;
      63'h004: Data = 32'hF84083EA;
      63'h008: Data = 32'hF84103EB;
      63'h00c: Data = 32'hF84183EC;
      63'h010: Data = 32'hF84203ED;
      63'h014: Data = 32'hAA0B014A;
      63'h018: Data = 32'h8A0A018C;
      63'h01c: Data = 32'hB400008C;
      63'h020: Data = 32'h8B0901AD;
      63'h024: Data = 32'hCB09018C;
      63'h028: Data = 32'h17FFFFFD;
      63'h02c: Data = 32'hF80203ED;
      63'h030:
      Data = 32'hF84203ED;  //One last load to place stored value on memdbus for test checking.

      /* Add code for your tests here */


      default: Data = 32'hXXXXXXXX;
    endcase

  end
endmodule

Lab09/SingleCycleProc.v
`timescale 1ns / 1ps
module singlecycle (
    input             resetl,
    input      [63:0] startpc,
    output reg [63:0] currentpc,
    output     [63:0] MemtoRegOut,  // this should be
    // attached to the
    // output of the
    // MemtoReg Mux
    input             CLK
);

  // Next PC connections
  wire [63:0] nextpc;  // The next PC, to be updated on clock cycle

  // Instruction Memory connections
  wire [31:0] instruction;  // The current instruction

  // Parts of instruction
  wire [ 4:0] rd;  // The destination register
  wire [ 4:0] rm;  // Operand 1
  wire [ 4:0] rn;  // Operand 2
  wire [10:0] opcode;

  //Added wires for MUXes
  wire [63:0] MuxToAlu;

  // Control wires
  wire        reg2loc;
  wire        alusrc;
  wire        mem2reg;
  wire        regwrite;
  wire        memread;
  wire        memwrite;
  wire        branch;
  wire        uncond_branch;
  wire [ 3:0] aluctrl;
  wire [ 1:0] signop;

  // Register file connections
  wire [63:0] regoutA;  // Output A
  wire [63:0] regoutB;  // Output B
  // ALU connections
  wire [63:0] aluout;
  wire        zero;
  //2nd ALU
  wire [63:0] Mux2Alu;

  // Sign Extender connections
  wire [63:0] extimm;

  //Data Memory connection
    always @(negedge CLK) begin
    if (resetl) currentpc <= #3 nextpc;
    else currentpc <= #3 startpc;
  	end

  //Wire
  wire        andout;
  wire        orout;
  wire [63:0] extmem;

  //assigning wires
  assign  rd = instruction[4:0];
  assign  rm = instruction[9:5];
  assign  opcode = instruction[31:21];
  assign  rn = reg2loc ? instruction[4:0] : instruction[20:16];
  assign  MuxToAlu = alusrc ? extimm : regoutB;
  assign  MemtoRegOut = mem2reg ? extmem : aluout;  //Added




  InstructionMemory imem (
      .Data(instruction),
      .Address(currentpc)
  );





  control control (
      .reg2loc(reg2loc),
      .alusrc(alusrc),
      .mem2reg(mem2reg),
      .regwrite(regwrite),
      .memread(memread),
      .memwrite(memwrite),
      .branch(branch),
      .uncond_branch(uncond_branch),
      .aluop(aluctrl),
      .signop(signop),
      .opcode(opcode)
  );

	ALU alu(
	.BusW(aluout), 
	.Zero(zero), 
	.BusA(regoutA), 
	.BusB(MuxToAlu), 
	.ALUCtrl(aluctrl)
	);
  // Parts of instruction
  RegisterFile regFile (
      .RA(rm),
      .RB(rn),
      .RW(rd),
      .BusW(MemtoRegOut),
      .RegWr(regwrite),
      .Clk(CLK),
      .BusA(regoutA),
      .BusB(regoutB)
  );


  SignExtender SignExtend (
      .Imm26 (instruction[25:0]),
      .BusImm(extimm),
      .Ctrl  (signop)
  );

  //MuxToALU wire


  DataMemory dmem (
      .ReadData(extmem),
      .Address(aluout),
      .WriteData(regoutB),
      .MemoryRead(memread),
      .MemoryWrite(memwrite),
      .Clock(CLK)
  );

  NextPClogic NPC (
      .NextPC(nextpc),
      .CurrentPC(currentpc),
      .SignExtImm64(extimm),
      .Branch(branch),
      .ALUZero(zero),
      .Uncondbranch(uncond_branch)
  );





  /*
    * Connect the remaining datapath elements below.
    * Do not forget any additional multiplexers that may be required.
    */



endmodule

Lab09/SingleCycleProcTest.v
`timescale 1ns / 1ps

`define STRLEN 32
`define HalfClockPeriod 60
`define ClockPeriod `HalfClockPeriod * 2

module SingleCycleProcTest_v;

   initial
     begin
        $dumpfile("singlecycle.vcd");
        $dumpvars;
     end

   // These tasks are used to check if a given test has passed and
   // confirm that all tests passed.
   task passTest;
      input [63:0] actualOut, expectedOut;
      input [`STRLEN*8:0] testType;
      inout [7:0] 	  passed;

      if(actualOut == expectedOut) begin $display ("%s passed", testType); passed = passed + 1; end
      else $display ("%s failed: 0x%x should be 0x%x", testType, actualOut, expectedOut);
   endtask

   task allPassed;
      input [7:0] passed;
      input [7:0] numTests;

      if(passed == numTests) $display ("All tests passed");
      else $display("Some tests failed: %d of %d passed", passed, numTests);
   endtask

   // Inputs
   reg 		  CLK;
   reg 		  Reset_L;
   reg [63:0] 	  startPC;
   reg [7:0] 	  passed;
   reg [15:0] 	  watchdog;

   // Outputs
   wire [63:0] 	  MemtoRegOut;
   wire [63:0] 	  currentPC;
   

   // Instantiate the Unit Under Test (UUT)
   singlecycle uut (
		    .CLK(CLK),
		    .resetl(Reset_L),
		    .startpc(startPC),
		    .currentpc(currentPC),
		    .MemtoRegOut(MemtoRegOut)
		    );

   initial begin
      // Initialize Inputs
      Reset_L = 1;
      startPC = 0;
      passed = 0;

      // Initialize Watchdog timer
      watchdog = 0;

      // Wait for global reset
      #(1 * `ClockPeriod);

      // Program 1
      #1
        Reset_L = 0; startPC =0;
      @(posedge CLK);
      @(negedge CLK);
      @(posedge CLK);
      Reset_L = 1;

      // ***********************************************************
      // This while loop will continue cycling the processor until the
      // PC reaches the final instruction in the first test.  If the
      // program forms an infinite loop, never reaching the end, the
      // watchdog timer will kick in and kill simulation after 64K
      // cycles.
      // ***********************************************************
		
      while (currentPC < 64'h30)
        begin
	   @(posedge CLK);  
		   $display("CurrentPC:%h",currentPC);
           //$display("MemtoReg:%h",MemtoRegOut);
	   @(negedge CLK);

        end
      
      passTest(MemtoRegOut, 64'hF, "Results of Program 1", passed);

      // ***********************************************************
      // Add your new tests here
      // ***********************************************************

      // Done
      allPassed(passed, 1);   // Be sure to change the one to match
      // the number of tests you add.
      $finish;
   end

   // Initialize the clock to be 0
   initial begin
      CLK = 0;
   end

   // The following is correct if clock starts at LOW level at StartTime //
   always begin
      #`HalfClockPeriod CLK = ~CLK;
      #`HalfClockPeriod CLK = ~CLK;
      watchdog = watchdog +1;
   end

   // Kill the simulation if the watchdog hits 64K cycles
   always @*
     if (watchdog == 16'hFF)
       begin
          $display("Watchdog Timer Expired.");
          $finish;
       end


endmodule

Lab09/singlecycle.vcd
$date
	Thu Nov 30 21:06:30 2023
$end
$version
	Icarus Verilog
$end
$timescale
	1ps
$end
$scope module SingleCycleProcTest_v $end
$var wire 64 ! currentPC [63:0] $end
$var wire 64 " MemtoRegOut [63:0] $end
$var reg 1 # CLK $end
$var reg 1 $ Reset_L $end
$var reg 8 % passed [7:0] $end
$var reg 64 & startPC [63:0] $end
$var reg 16 ' watchdog [15:0] $end
$scope module uut $end
$var wire 1 # CLK $end
$var wire 1 $ resetl $end
$var wire 64 ( startpc [63:0] $end
$var wire 1 ) zero $end
$var wire 1 * uncond_branch $end
$var wire 2 + signop [1:0] $end
$var wire 5 , rn [4:0] $end
$var wire 5 - rm [4:0] $end
$var wire 1 . regwrite $end
$var wire 64 / regoutB [63:0] $end
$var wire 64 0 regoutA [63:0] $end
$var wire 1 1 reg2loc $end
$var wire 5 2 rd [4:0] $end
$var wire 11 3 opcode [10:0] $end
$var wire 64 4 nextpc [63:0] $end
$var wire 1 5 memwrite $end
$var wire 1 6 memread $end
$var wire 1 7 mem2reg $end
$var wire 32 8 instruction [31:0] $end
$var wire 64 9 extmem [63:0] $end
$var wire 64 : extimm [63:0] $end
$var wire 1 ; branch $end
$var wire 1 < alusrc $end
$var wire 64 = aluout [63:0] $end
$var wire 4 > aluctrl [3:0] $end
$var wire 64 ? MuxToAlu [63:0] $end
$var wire 64 @ MemtoRegOut [63:0] $end
$var reg 64 A currentpc [63:0] $end
$scope module NPC $end
$var wire 64 B CurrentPC [63:0] $end
$var wire 1 * Uncondbranch $end
$var wire 64 C Tmpimm [63:0] $end
$var wire 64 D SignExtImm64 [63:0] $end
$var wire 1 ; Branch $end
$var wire 1 ) ALUZero $end
$var reg 64 E NextPC [63:0] $end
$upscope $end
$scope module SignExtend $end
$var wire 26 F Imm26 [25:0] $end
$var wire 2 G Ctrl [1:0] $end
$var reg 64 H BusImm [63:0] $end
$var reg 1 I extBit $end
$upscope $end
$scope module alu $end
$var wire 64 J BusB [63:0] $end
$var wire 1 ) Zero $end
$var wire 64 K BusA [63:0] $end
$var wire 4 L ALUCtrl [3:0] $end
$var reg 64 M BusW [63:0] $end
$upscope $end
$scope module control $end
$var wire 11 N opcode [10:0] $end
$var reg 4 O aluop [3:0] $end
$var reg 1 < alusrc $end
$var reg 1 ; branch $end
$var reg 1 7 mem2reg $end
$var reg 1 6 memread $end
$var reg 1 5 memwrite $end
$var reg 1 1 reg2loc $end
$var reg 1 . regwrite $end
$var reg 2 P signop [1:0] $end
$var reg 1 * uncond_branch $end
$upscope $end
$scope module dmem $end
$var wire 64 Q Address [63:0] $end
$var wire 1 # Clock $end
$var wire 1 6 MemoryRead $end
$var wire 1 5 MemoryWrite $end
$var wire 64 R WriteData [63:0] $end
$var reg 64 S ReadData [63:0] $end
$scope task initset $end
$var reg 64 T addr [63:0] $end
$var reg 64 U data [63:0] $end
$upscope $end
$upscope $end
$scope module imem $end
$var wire 64 V Address [63:0] $end
$var reg 32 W Data [31:0] $end
$upscope $end
$scope module regFile $end
$var wire 64 X BusW [63:0] $end
$var wire 1 # Clk $end
$var wire 5 Y RA [4:0] $end
$var wire 5 Z RB [4:0] $end
$var wire 5 [ RW [4:0] $end
$var wire 1 . RegWr $end
$var wire 64 \ BusB [63:0] $end
$var wire 64 ] BusA [63:0] $end
$upscope $end
$upscope $end
$scope task allPassed $end
$var reg 8 ^ numTests [7:0] $end
$var reg 8 _ passed [7:0] $end
$upscope $end
$scope task passTest $end
$var reg 64 ` actualOut [63:0] $end
$var reg 64 a expectedOut [63:0] $end
$var reg 8 b passed [7:0] $end
$var reg 257 c testType [256:0] $end
$upscope $end
$upscope $end
$enddefinitions $end
#0
$dumpvars
bx c
bx b
bx a
bx `
bx _
bx ^
bx ]
bx \
bx [
bx Z
bx Y
bx X
bx W
bx V
b0 U
b100000 T
bx S
bx R
bx Q
bx P
bx O
bx N
bx M
bx L
bx K
bx J
xI
bx H
bx G
bx F
bx E
bx D
bx00 C
bx B
bx A
bx @
bx ?
bx >
bx =
x<
x;
bx :
bx 9
bx 8
x7
x6
x5
bx 4
bx 3
bx 2
x1
bx 0
bx /
x.
bx -
bx ,
bx +
x*
x)
b0 (
b0 '
b0 &
b0 %
1$
0#
bx "
bx !
$end
#2000
b0xxxxxxxxxxxxxxxxxxxxxxxxxxxxxxxx /
b0xxxxxxxxxxxxxxxxxxxxxxxxxxxxxxxx R
b0xxxxxxxxxxxxxxxxxxxxxxxxxxxxxxxx \
b0xxxxxxxxxxxxxxxxxxxxxxxxxxxxxxxx 0
b0xxxxxxxxxxxxxxxxxxxxxxxxxxxxxxxx K
b0xxxxxxxxxxxxxxxxxxxxxxxxxxxxxxxx ]
#60000
1#
#120000
b1 '
0#
#121000
0$
#180000
1#
#240000
b10 '
0#
#243000
b0 C
b0 ?
b0 J
b0 :
b0 D
b0 H
0I
b1 +
b1 G
b1 P
b10 >
b10 L
b10 O
0;
05
16
1.
17
1<
b100 4
b100 E
b0x00x ,
b0x00x Z
b10000000000001111101001 F
b11111000010 3
b11111000010 N
b11111 -
b11111 Y
b1001 2
b1001 [
b11111000010000000000001111101001 8
b11111000010000000000001111101001 W
b0 !
b0 A
b0 B
b0 V
#245000
1)
b0 =
b0 M
b0 Q
b0 0
b0 K
b0 ]
#300000
b1 "
b1 @
b1 X
b1 9
b1 S
1$
1#
#360000
b11 '
0#
#363000
b1000 4
b1000 E
0)
b1000 =
b1000 M
b1000 Q
b100000 C
b1000 ?
b1000 J
b1000 :
b1000 D
b1000 H
b0x0x0 ,
b0x0x0 Z
b10000001000001111101010 F
b1010 2
b1010 [
b11111000010000001000001111101010 8
b11111000010000001000001111101010 W
b100 !
b100 A
b100 B
b100 V
#420000
b1010 "
b1010 @
b1010 X
b1010 9
b1010 S
1#
#480000
b100 '
0#
#483000
b1100 4
b1100 E
b10000 =
b10000 M
b10000 Q
b1000000 C
b10000 ?
b10000 J
b10000 :
b10000 D
b10000 H
b0x0x1 ,
b0x0x1 Z
b10000010000001111101011 F
b1011 2
b1011 [
b11111000010000010000001111101011 8
b11111000010000010000001111101011 W
b1000 !
b1000 A
b1000 B
b1000 V
#540000
b101 "
b101 @
b101 X
b101 9
b101 S
1#
#600000
b101 '
0#
#603000
b10000 4
b10000 E
b11000 =
b11000 M
b11000 Q
b1100000 C
b11000 ?
b11000 J
b11000 :
b11000 D
b11000 H
b0xx0x ,
b0xx0x Z
b10000011000001111101100 F
b1100 2
b1100 [
b11111000010000011000001111101100 8
b11111000010000011000001111101100 W
b1100 !
b1100 A
b1100 B
b1100 V
#660000
b111111111011111010100111110111101010110110111110111011111111 "
b111111111011111010100111110111101010110110111110111011111111 @
b111111111011111010100111110111101010110110111110111011111111 X
b111111111011111010100111110111101010110110111110111011111111 9
b111111111011111010100111110111101010110110111110111011111111 S
1#
#720000
b110 '
0#
#723000
b10100 4
b10100 E
b100000 =
b100000 M
b100000 Q
b10000000 C
b100000 ?
b100000 J
b100000 :
b100000 D
b100000 H
b0xxxx ,
b0xxxx Z
b10000100000001111101101 F
b1101 2
b1101 [
b11111000010000100000001111101101 8
b11111000010000100000001111101101 W
b10000 !
b10000 A
b10000 B
b10000 V
#780000
b0 "
b0 @
b0 X
b0 9
b0 S
1#
#840000
b111 '
0#
#843000
x)
b0xxxxxxxxxxxxxxxxxxxxxxxxxxxxxxxx "
b0xxxxxxxxxxxxxxxxxxxxxxxxxxxxxxxx @
b0xxxxxxxxxxxxxxxxxxxxxxxxxxxxxxxx X
bx +
bx G
bx P
b1 >
b1 L
b1 O
0*
06
07
0<
01
b11000 4
b11000 E
b0xxxxxxxxxxxxxxxxxxxxxxxxxxxxxxxx =
b0xxxxxxxxxxxxxxxxxxxxxxxxxxxxxxxx M
b0xxxxxxxxxxxxxxxxxxxxxxxxxxxxxxxx Q
b1011000000 C
b0xxxxxxxxxxxxxxxxxxxxxxxxxxxxxxxx ?
b0xxxxxxxxxxxxxxxxxxxxxxxxxxxxxxxx J
b10110000 :
b10110000 D
b10110000 H
b1011 ,
b1011 Z
b10000010110000000101001010 F
b10101010000 3
b10101010000 N
b1010 -
b1010 Y
b1010 2
b1010 [
b10101010000010110000000101001010 8
b10101010000010110000000101001010 W
b10100 !
b10100 A
b10100 B
b10100 V
#845000
0)
b1111 "
b1111 @
b1111 X
b101 ?
b101 J
b1111 =
b1111 M
b1111 Q
b101 /
b101 R
b101 \
b1010 0
b1010 K
b1010 ]
#900000
1#
#960000
b1000 '
0#
#963000
1)
b0 "
b0 @
b0 X
b0 =
b0 M
b0 Q
b0 >
b0 L
b0 O
b11100 4
b11100 E
b1010 ,
b1010 Z
b10000010100000000110001100 F
b10001010000 3
b10001010000 N
b1100 -
b1100 Y
b1100 2
b1100 [
b10001010000010100000000110001100 8
b10001010000010100000000110001100 W
b11000 !
b11000 A
b11000 B
b11000 V
#965000
0)
b1111 "
b1111 @
b1111 X
b1111 ?
b1111 J
b1111 =
b1111 M
b1111 Q
b1111 /
b1111 R
b1111 \
b11101010110110111110111011111111 0
b11101010110110111110111011111111 K
b11101010110110111110111011111111 ]
#1020000
1#
#1080000
b1001 '
0#
#1083000
b10000 C
b100 :
b100 D
b100 H
b0xxxx "
b0xxxx @
b0xxxx X
b11 +
b11 G
b11 P
b111 >
b111 L
b111 O
1;
0.
x7
11
b100000 4
b100000 E
b1100 ,
b1100 Z
b10001100 F
b10110100000 3
b10110100000 N
b100 -
b100 Y
b10110100000000000000000010001100 8
b10110100000000000000000010001100 W
b11100 !
b11100 A
b11100 B
b11100 V
#1085000
b0xxxxxxxxxxxxxxxxxxxxxxxxxxxxxxxx 0
b0xxxxxxxxxxxxxxxxxxxxxxxxxxxxxxxx K
b0xxxxxxxxxxxxxxxxxxxxxxxxxxxxxxxx ]
#1140000
1#
#1200000
b1010 '
0#
#1203000
x)
bx =
bx M
bx Q
bx "
bx @
bx X
bx +
bx G
bx P
b10 >
b10 L
b10 O
0;
1.
07
01
b100100 4
b100100 E
b10010000000110100 C
b100100000001101 :
b100100000001101 D
b100100000001101 H
b1001 ,
b1001 Z
b11000010010000000110101101 F
b10001011000 3
b10001011000 N
b1101 -
b1101 Y
b1101 2
b1101 [
b10001011000010010000000110101101 8
b10001011000010010000000110101101 W
b100000 !
b100000 A
b100000 B
b100000 V
#1205000
0)
b1 "
b1 @
b1 X
b1 ?
b1 J
b1 =
b1 M
b1 Q
b1 /
b1 R
b1 \
b0 0
b0 K
b0 ]
#1260000
1#
#1320000
b1011 '
0#
#1323000
b1111111111111111111111111111111111111111111111111111111111111111 "
b1111111111111111111111111111111111111111111111111111111111111111 @
b1111111111111111111111111111111111111111111111111111111111111111 X
b1111111111111111111111111111111111111111111111111111111111111111 =
b1111111111111111111111111111111111111111111111111111111111111111 M
b1111111111111111111111111111111111111111111111111111111111111111 Q
b110 >
b110 L
b110 O
b101000 4
b101000 E
b11000010010000000110001100 F
b11001011000 3
b11001011000 N
b1100 -
b1100 Y
b1100 2
b1100 [
b11001011000010010000000110001100 8
b11001011000010010000000110001100 W
b100100 !
b100100 A
b100100 B
b100100 V
#1325000
b1110 "
b1110 @
b1110 X
b1110 =
b1110 M
b1110 Q
b1111 0
b1111 K
b1111 ]
#1380000
1#
#1440000
b1100 '
0#
