Lab09/NextPClogic.v
`timescale 1ns / 1ps
module NextPClogic(NextPC, CurrentPC, SignExtImm64, Branch, ALUZero, Uncondbranch); 
   input [63:0] CurrentPC, SignExtImm64; 
   input 	Branch, ALUZero, Uncondbranch; 
   output reg [63:0] NextPC; 
   wire [63:0] Tmpimm;
	assign Tmpimm = SignExtImm64 << 2;
   always @(*)
		begin
		if(Uncondbranch) begin
			NextPC <= CurrentPC + Tmpimm;
		end else if (Branch) begin
			if (ALUZero) begin
				NextPC <= CurrentPC + Tmpimm;
			end else begin
				NextPC <= CurrentPC + 4;
			end
		end else begin
			NextPC <= CurrentPC + 4;
		end
	end

endmodule

Lab09/DataMemory.v
`timescale 1ns / 1ps

`define SIZE 1024

module DataMemory(ReadData , Address , WriteData , MemoryRead , MemoryWrite , Clock);
   input [63:0]      WriteData;
   input [63:0]      Address;
   input             Clock, MemoryRead, MemoryWrite;
   output reg [63:0] ReadData;

   reg [7:0] 	     memBank [`SIZE-1:0];


   // This task is used to write arbitrary data to the Data Memory by
   // the intialization block.
   task initset;
      input [63:0] addr;
      input [63:0] data;
      begin
	 memBank[addr] =  data[63:56] ; // Big-endian for the win...
	 memBank[addr+1] =  data[55:48];
	 memBank[addr+2] =  data[47:40];
	 memBank[addr+3] =  data[39:32];
	 memBank[addr+4] =  data[31:24];
	 memBank[addr+5] =  data[23:16];
	 memBank[addr+6] =  data[15:8];
	 memBank[addr+7] =  data[7:0];
      end
   endtask


   initial
     begin
        // preseting some data in the data memory used by test #1

        // Address 0x0 gets 0x1
        initset( 64'h0,  64'h1);  //Counter variable
        initset( 64'h8,  64'ha);  //Part of mask
        initset( 64'h10, 64'h5);  //Other part of mask
        initset( 64'h18, 64'h0ffbea7deadbeeff); //big constant
        initset( 64'h20, 64'h0); //clearing space

        // Add any data you need for your tests here.
        initset( 64'h22, 64'h123456789abcdef0)

     end

   // This always block reads the data memory and places a double word
   // on the ReadData bus.
   always @(posedge Clock)
     begin
        if(MemoryRead)
          begin
             ReadData[63:56] <=  memBank[Address];
             ReadData[55:48] <=  memBank[Address+1];
             ReadData[47:40] <=  memBank[Address+2];
             ReadData[39:32] <=  memBank[Address+3];
             ReadData[31:24] <=  memBank[Address+4];
             ReadData[23:16] <=  memBank[Address+5];
             ReadData[15:8] <=  memBank[Address+6];
             ReadData[7:0] <=  memBank[Address+7];
          end
     end

   // This always block takes data from the WriteData bus and writes
   // it into the DataMemory.
   always @(posedge Clock)
     begin
        if(MemoryWrite)
          begin
             memBank[Address] <= #3 WriteData[63:56] ;
             memBank[Address+1] <= #3 WriteData[55:48];
             memBank[Address+2] <= #3 WriteData[47:40];
             memBank[Address+3] <= #3 WriteData[39:32];
             memBank[Address+4] <= #3 WriteData[31:24];
             memBank[Address+5] <= #3 WriteData[23:16];
             memBank[Address+6] <= #3 WriteData[15:8];
             memBank[Address+7] <= #3 WriteData[7:0];
             // Could be useful for debugging:
             // $display("Writing Address:%h Data:%h",Address, WriteData);
          end
     end
     //$display("Dmem:%h",ReadData);
endmodule

Lab09/SignExtender.v
module SignExtender(BusImm, Imm26, Ctrl); 
   output reg [63:0] BusImm; 
   input [25:0]  Imm26;
   input [1:0]	Ctrl; 
   
   reg extBit; 
   always @(Ctrl, Imm26)
   begin
		case(Ctrl)
			2'b00: /* I-Type instructions */
				begin
				extBit = 0;
			    BusImm = {{52{extBit}}, Imm26[21:10]};
			    end
			2'b01: /* D-Type instructions */
				begin
				extBit = Imm26[20];
				BusImm = {{55{extBit}}, Imm26[20:12]};
				end
			2'b10: /* B instructions */
				begin
				extBit = Imm26[25];
				BusImm = {{38{extBit}}, Imm26[25:0]};
				end
			2'b11: /* CBZ instructions */
				begin
				extBit = Imm26[23]; 
				BusImm = {{45{extBit}}, Imm26[23:5]};
				end
		endcase
	end
endmodule

Lab09/RegisterFile.v


module RegisterFile(BusA, BusB, BusW, RA, RB, RW, RegWr, Clk);
    output [63:0] BusA;
    output [63:0] BusB;
    input [63:0] BusW;
    input [4:0] RW;
    input [4:0] RA;
    input [4:0] RB;
    input RegWr;
    input Clk;
    reg [63:0] registers [31:0];
	
	
	assign #2 BusA = (RA==31) ? 0 : registers[RA];
	assign #2 BusB = (RB==31) ? 0 : registers[RB];
     
    always @ (negedge Clk) begin
        if(RegWr && (RW != 31))
            registers[RW] <= #3 BusW;
            registers[31] <= #3 0; 
        $display("Ra:%d", RA);    
        $display("Rb:%d", RB);
        $display("Rw:%d", RW);
        $display("BusA:%h", BusA);
        $display("BusB:%h", BusB);
        $display("BusW:%h", BusW);
    end
    
    
	

    

endmodule

Lab09/ALU.v
`define AND   4'b0000
`define OR    4'b0001
`define ADD   4'b0010
`define SUB   4'b0110
`define PassB 4'b0111

module ALU(BusW, BusA, BusB, ALUCtrl, Zero);
    
    output  [63:0] BusW;
    input   [63:0] BusA, BusB;
    input   [3:0] ALUCtrl;
    output  Zero;
    
    reg     [63:0] BusW;
    
    always @(ALUCtrl or BusA or BusB) begin
        case(ALUCtrl)
            4'b0000: begin /* AND */
                BusW = BusA & BusB;
            end
            4'b0001: begin /* OR */
				BusW = BusA | BusB;
			end
			4'b0010: begin /*ADD */
				BusW = BusA + BusB;
			end
			4'b0110: begin /* SUB */
				BusW = BusA - BusB;
			end
			4'b0111: begin /*PassB */
				BusW = BusB;
			end
			
        endcase
        $display("ALUOUT:%h", BusW);
    end
	
    assign Zero = (BusW ? 0 : 1);
endmodule

Lab09/SingleCycleControl.v
`define OPCODE_ANDREG 11'b?0001010???
`define OPCODE_ORRREG 11'b?0101010???
`define OPCODE_ADDREG 11'b?0?01011???
`define OPCODE_SUBREG 11'b?1?01011???

`define OPCODE_ADDIMM 11'b?0?10001???
`define OPCODE_SUBIMM 11'b?1?10001???


`define OPCODE_B      11'b?00101?????
`define OPCODE_CBZ    11'b?011010????

`define OPCODE_LDUR   11'b11111000010
`define OPCODE_STUR   11'b??111000000

`define OPCODE_MOVZ   11'b110100101??

`timescale 1ns / 1ps
module control(
    output reg reg2loc,
    output reg alusrc,
    output reg mem2reg,
    output reg regwrite,
    output reg memread,
    output reg memwrite,
    output reg branch,
    output reg uncond_branch,
    output reg [3:0] aluop,
    output reg [1:0] signop,
    input [10:0] opcode
);

always @(*)
begin
    casez (opcode)
    
    `OPCODE_ANDREG : 
	begin // AND
	    reg2loc       <= 1'b0;
            alusrc        <= 1'b0;
            mem2reg       <= 1'b0;
            regwrite      <= 1'b1;
            memread       <= 1'b0;
            memwrite      <= 1'b0;
            branch        <= 1'b0;
            uncond_branch <= 1'b0;
            aluop         <= 4'b0000;
            signop        <= 2'bxx;
	end
		
    `OPCODE_ORRREG : // ORR
	begin
	    reg2loc       <= 1'b0;
            alusrc        <= 1'b0;
            mem2reg       <= 1'b0;
            regwrite      <= 1'b1;
            memread       <= 1'b0;
            memwrite      <= 1'b0;
            branch        <= 1'b0;
            uncond_branch <= 1'b0;
            aluop         <= 4'b0001;
            signop        <= 2'bxx;
	end
		
    `OPCODE_ADDREG : // ADDR
	begin
	    reg2loc       <= 1'b0;
            alusrc        <= 1'b0;
            mem2reg       <= 1'b0;
            regwrite      <= 1'b1;
            memread       <= 1'b0;
            memwrite      <= 1'b0;
            branch        <= 1'b0;
            uncond_branch <= 1'b0;
            aluop         <= 4'b0010;
            signop        <= 2'bxx;
	end
		
    `OPCODE_SUBREG : // SUBR
	begin
	    reg2loc       <= 1'b0;
            alusrc        <= 1'b0;
            mem2reg       <= 1'b0;
            regwrite      <= 1'b1;
            memread       <= 1'b0;
            memwrite      <= 1'b0;
            branch        <= 1'b0;
            uncond_branch <= 1'b0;
            aluop         <= 4'b0110;
            signop        <= 2'bxx;
        end
		
    `OPCODE_ADDIMM : // ADDI			
	begin
		    reg2loc       <= 1'bx;
            alusrc        <= 1'b1;
            mem2reg       <= 1'b0;
            regwrite      <= 1'b1;
            memread       <= 1'b0;
            memwrite      <= 1'b0;
            branch        <= 1'b0;
            uncond_branch <= 1'b0;
            aluop         <= 4'b0010;
            signop        <= 2'b00;
		end
		
    `OPCODE_SUBIMM : // SUBI			
	begin
	    reg2loc       <= 1'bx;
            alusrc        <= 1'b1;
            mem2reg       <= 1'b0;
            regwrite      <= 1'b1;
            memread       <= 1'b0;
            memwrite      <= 1'b0;
            branch        <= 1'b0;
            uncond_branch <= 1'b0;
            aluop         <= 4'b0110;
            signop        <= 2'b00;
	end
		
		
    `OPCODE_B : // B
	begin
	    reg2loc       <= 1'bx;
            alusrc        <= 1'b0;
            mem2reg       <= 1'bx;
            regwrite      <= 1'b0;
            memread       <= 1'b0;
            memwrite      <= 1'b0;
            branch        <= 1'b0;
            uncond_branch <= 1'b1;
            aluop         <= 4'b0111;
            signop        <= 2'b10;
	end
		
    `OPCODE_CBZ : // CBZ
	begin
	    reg2loc       <= 1'b1;
            alusrc        <= 1'b0;
            mem2reg       <= 1'bx;
            regwrite      <= 1'b0;
            memread       <= 1'b0;
            memwrite      <= 1'b0;
            branch        <= 1'b1;
            uncond_branch <= 1'b0;
            aluop         <= 4'b0111;
            signop        <= 2'b11;
	end
		
    `OPCODE_LDUR : // LDUR
	  begin
	    reg2loc       <= 1'bx;
            alusrc        <= 1'b1;
            mem2reg       <= 1'b1;
            regwrite      <= 1'b1;
            memread       <= 1'b1;
            memwrite      <= 1'b0;
            branch        <= 1'b0;
            uncond_branch <= 1'bx;
            aluop         <= 4'b0010;
            signop        <= 2'b01;
	  end
		
    `OPCODE_STUR : //STUR
	  begin
	    reg2loc       <= 1'b1;
            alusrc        <= 1'b1;
            mem2reg       <= 1'bx;
            regwrite      <= 1'b0;
            memread       <= 1'b0;
            memwrite      <= 1'b1;
            branch        <= 1'b0;
            uncond_branch <= 1'b0;
            aluop         <= 4'b0010;
            signop        <= 2'b01;
	  end

    `OPCODE_MOVZ : // MOVZ
	begin
	    reg2loc       <= 1'b0;
            alusrc        <= 1'b1;
            mem2reg       <= 1'b0;
            regwrite      <= 1'b1;
            memread       <= 1'b0;
            memwrite      <= 1'b0;
            branch        <= 1'b0;
            uncond_branch <= 1'b0;
            aluop         <= 4'b0111;
            signop        <= {1'b1, opcode[1:0]};
	end

        default:
        begin
            reg2loc       <= 1'bx;
            alusrc        <= 1'bx;
            mem2reg       <= 1'b1;
            regwrite      <= 1'b0;
            memread       <= 1'b0;
            memwrite      <= 1'b0;
            branch        <= 1'b0;
            uncond_branch <= 1'b0;
            aluop         <= 4'bxxxx;
            signop        <= 2'bxx;
        end
        
    endcase
    
    //$display("mem2reg:%h", mem2reg);
    //$display("reg2loc:%h", reg2loc);
    //$display("regwrite:%h", regwrite);
    //$display("memread:%h", memread);
    //$display("memwrite:%h", memwrite);
    //$display("branch:%h", branch);
    //$display("uncond_branch:%h", uncond_branch);
    //$display("aluop:%h", aluop);
    //$display("signop:%h", signop);
    

end

endmodule

Lab09/InstructionMemory.v
  `timescale 1ns / 1ps
/*
 * Module: InstructionMemory
 *
 * Implements read-only instruction memory
 * 
 */
module InstructionMemory (
    Data,
    Address
);
  parameter T_rd = 20;
  parameter MemSize = 40;

  output [31:0] Data;
  input [63:0] Address;
  reg [31:0] Data;

  /*
    * ECEN 350 Processor Test Functions
    * Texas A&M University
    */

  always @(Address) begin

    case (Address)

      /* Test Program 1:
	 * Program loads constants from the data memory. Uses these constants to test
	 * the following instructions: LDUR, ORR, AND, CBZ, ADD, SUB, STUR and B.
	 * 
	 * Assembly code for test:
	 * 
	 * 0: LDUR X9, [XZR, 0x0]    //Load 1 into x9
	 * 4: LDUR X10, [XZR, 0x8]   //Load a into x10
	 * 8: LDUR X11, [XZR, 0x10]  //Load 5 into x11
	 * C: LDUR X12, [XZR, 0x18]  //Load big constant into x12
	 * 10: LDUR X13, [XZR, 0x20]  //load a 0 into X13
	 * 
	 * 14: ORR X10, X10, X11  //Create mask of 0xf
	 * 18: AND X12, X12, X10  //Mask off low order bits of big constant
	 * 
	 * loop:
	 * 1C: CBZ X12, end  //while X12 is not 0
	 * 20: ADD X13, X13, X9  //Increment counter in X13
	 * 24: SUB X12, X12, X9  //Decrement remainder of big constant in X12
	 * 28: B loop  //Repeat till X12 is 0
	 * 2C: STUR X13, [XZR, 0x20]  //store back the counter value into the memory location 0x20
	 */


      /*63'h000: Data = 32'hF84003E9;
      63'h004: Data = 32'hF84083EA;
      63'h008: Data = 32'hF84103EB;
      63'h00c: Data = 32'hF84183EC;
      63'h010: Data = 32'hF84203ED;
      63'h014: Data = 32'hAA0B014A;
      63'h018: Data = 32'h8A0A018C;
      63'h01c: Data = 32'hB400008C;
      63'h020: Data = 32'h8B0901AD;
      63'h024: Data = 32'hCB09018C;
      63'h028: Data = 32'h17FFFFFD;
      63'h02c: Data = 32'hF80203ED;
      63'h030:
      Data = 32'hF84203ED;  //One last load to place stored value on memdbus for test checking.
      */
      /* Add code for your tests here */

      /*
      Movz Test
      1. Movz 1234 into register x9
      1-2. set X11 to 12* 16
      2. LSL x9 by 12 * 16
      3. Movz 5678 into register x10
      3-2 set X11 to 8 * 16
      4. LSL x10 by 8
      5. add X9 and X10
      6. Movz 9ABC into register x10
      6-2 set X11 to 4
      7. LSL x10 by 4
      8. add X9 and X10
      9. Movz DEF0 into register x10
      10. add X9 and X10
      */

      63'h000: Data = {11'b11010010100, 16'h1234, 5'b01001};//Movz 1234 into register x9
      63'h004: Data = {11'b11010010100, 16'h00C0, 5'b01011};//Movz X11 to 12* 16
      63'h008: Data = {11'b11010011011, 5'b01001,6'b000000, 5'b01011, 5'b01001};//LSL x9 by 12 * 16
      63'h00C: Data = {11'b11010010100, 16'h5678, 5'b01010};//Movz 5678 into register x10
      63'h004: Data = {11'b11010010100, 16'h0080, 5'b01011};//Movz X11 to 8
      63'h010: Data = {11'b11010010100, 5'b01010, 6'b000000, 5'b01011, 5'b01010};//LSL x10 by 8 * 16
      63'h014: Data = {11'b10001011000, 4'b0101, 5'b01001, 5'b01010};//add X9 and X10
      63'h018: Data = {11'b11010010100, 16'h9ABC, 5'b01010};//Movz 9ABC into register x10
      63'h01C: Data = {11'b11010010100, 16'h0040, 5'b01011};//Movz X11 to 4
      63'h020: Data = {11'b11010010100, 5'b01010, 6'b000000, 5'b01011, 5'b01010};//LSL x10 by 4
      63'h024: Data = {11'b10001011000, 4'b0101, 5'b01001, 5'b01010};//add X9 and X10
      63'h028: Data = {11'b11010010100, 16'hDEF0, 5'b01010};//Movz DEF0 into register x10
      63'h02C: Data = {11'b10001011000, 4'b0101, 5'b01001, 5'b01010};//add X9 and X10
      63'h030: Data = {11'bxx111000000,9'h28,2'h0,5'd31,5'b01001}; //stur x9 [xzr,0x28]
      63'h034: Data = {11'bxx111000010,9'h28,2'h0,5'd31,5'h10};//ldur x10, [xzr, 0x28]

     
      
      



      default: Data = 32'hXXXXXXXX;
    endcase

  end
endmodule

Lab09/SingleCycleProc.v
`timescale 1ns / 1ps
module singlecycle (
    input             resetl,
    input      [63:0] startpc,
    output reg [63:0] currentpc,
    output     [63:0] MemtoRegOut,  // this should be
    // attached to the
    // output of the
    // MemtoReg Mux
    input             CLK
);

  // Next PC connections
  wire [63:0] nextpc;  // The next PC, to be updated on clock cycle

  // Instruction Memory connections
  wire [31:0] instruction;  // The current instruction

  // Parts of instruction
  wire [ 4:0] rd;  // The destination register
  wire [ 4:0] rm;  // Operand 1
  wire [ 4:0] rn;  // Operand 2
  wire [10:0] opcode;

  //Added wires for MUXes
  wire [63:0] MuxToAlu;

  // Control wires
  wire        reg2loc;
  wire        alusrc;
  wire        mem2reg;
  wire        regwrite;
  wire        memread;
  wire        memwrite;
  wire        branch;
  wire        uncond_branch;
  wire [ 3:0] aluctrl;
  wire [ 1:0] signop;

  // Register file connections
  wire [63:0] regoutA;  // Output A
  wire [63:0] regoutB;  // Output B
  // ALU connections
  wire [63:0] aluout;
  wire        zero;
  //2nd ALU
  wire [63:0] Mux2Alu;

  // Sign Extender connections
  wire [63:0] extimm;

  //Data Memory connection
    always @(negedge CLK) begin
    if (resetl) currentpc <= #3 nextpc;
    else currentpc <= #3 startpc;
  	end

  //Wire
  wire        andout;
  wire        orout;
  wire [63:0] extmem;

  //assigning wires
  assign  rd = instruction[4:0];
  assign  rm = instruction[9:5];
  assign  opcode = instruction[31:21];
  assign  rn = reg2loc ? instruction[4:0] : instruction[20:16];
  assign  MuxToAlu = alusrc ? extimm : regoutB;
  assign  MemtoRegOut = mem2reg ? extmem : aluout;  //Added




  InstructionMemory imem (
      .Data(instruction),
      .Address(currentpc)
  );





  control control (
      .reg2loc(reg2loc),
      .alusrc(alusrc),
      .mem2reg(mem2reg),
      .regwrite(regwrite),
      .memread(memread),
      .memwrite(memwrite),
      .branch(branch),
      .uncond_branch(uncond_branch),
      .aluop(aluctrl),
      .signop(signop),
      .opcode(opcode)
  );

	ALU alu(
	.BusW(aluout), 
	.Zero(zero), 
	.BusA(regoutA), 
	.BusB(MuxToAlu), 
	.ALUCtrl(aluctrl)
	);
  // Parts of instruction
  RegisterFile regFile (
      .RA(rm),
      .RB(rn),
      .RW(rd),
      .BusW(MemtoRegOut),
      .RegWr(regwrite),
      .Clk(CLK),
      .BusA(regoutA),
      .BusB(regoutB)
  );


  SignExtender SignExtend (
      .Imm26 (instruction[25:0]),
      .BusImm(extimm),
      .Ctrl  (signop)
  );

  //MuxToALU wire


  DataMemory dmem (
      .ReadData(extmem),
      .Address(aluout),
      .WriteData(regoutB),
      .MemoryRead(memread),
      .MemoryWrite(memwrite),
      .Clock(CLK)
  );

  NextPClogic NPC (
      .NextPC(nextpc),
      .CurrentPC(currentpc),
      .SignExtImm64(extimm),
      .Branch(branch),
      .ALUZero(zero),
      .Uncondbranch(uncond_branch)
  );





  /*
    * Connect the remaining datapath elements below.
    * Do not forget any additional multiplexers that may be required.
    */



endmodule

Lab09/SingleCycleProcTest.v
`timescale 1ns / 1ps

`define STRLEN 32
`define HalfClockPeriod 60
`define ClockPeriod `HalfClockPeriod * 2

module SingleCycleProcTest_v;

   initial
     begin
        $dumpfile("singlecycle.vcd");
        $dumpvars;
     end

   // These tasks are used to check if a given test has passed and
   // confirm that all tests passed.
   task passTest;
      input [63:0] actualOut, expectedOut;
      input [`STRLEN*8:0] testType;
      inout [7:0] 	  passed;

      if(actualOut == expectedOut) begin $display ("%s passed", testType); passed = passed + 1; end
      else $display ("%s failed: 0x%x should be 0x%x", testType, actualOut, expectedOut);
   endtask

   task allPassed;
      input [7:0] passed;
      input [7:0] numTests;

      if(passed == numTests) $display ("All tests passed");
      else $display("Some tests failed: %d of %d passed", passed, numTests);
   endtask

   // Inputs
   reg 		  CLK;
   reg 		  Reset_L;
   reg [63:0] 	  startPC;
   reg [7:0] 	  passed;
   reg [15:0] 	  watchdog;

   // Outputs
   wire [63:0] 	  MemtoRegOut;
   wire [63:0] 	  currentPC;
   

   // Instantiate the Unit Under Test (UUT)
   singlecycle uut (
		    .CLK(CLK),
		    .resetl(Reset_L),
		    .startpc(startPC),
		    .currentpc(currentPC),
		    .MemtoRegOut(MemtoRegOut)
		    );

   initial begin
      // Initialize Inputs
      Reset_L = 1;
      startPC = 0;
      passed = 0;

      // Initialize Watchdog timer
      watchdog = 0;

      // Wait for global reset
      #(1 * `ClockPeriod);

      // Program 1
      #1
        Reset_L = 0; startPC =0;
      @(posedge CLK);
      @(negedge CLK);
      @(posedge CLK);
      Reset_L = 1;

      // ***********************************************************
      // This while loop will continue cycling the processor until the
      // PC reaches the final instruction in the first test.  If the
      // program forms an infinite loop, never reaching the end, the
      // watchdog timer will kick in and kill simulation after 64K
      // cycles.
      // ***********************************************************
		
      while (currentPC <64'h34)
        begin
	   @(posedge CLK);  
		   $display("CurrentPC:%h\nMemtoRegOut:%h",currentPC, MemtoRegOut);
           //$display("MemtoReg:%h",MemtoRegOut);
	   @(negedge CLK);

        end
      
      //passTest(MemtoRegOut, 64'hF, "Results of Program 1", passed);
      passTest(MemtoRegOut, 64'h123456789abcdef0, "Results of Program 1", passed);

      // ***********************************************************
      // Add your new tests here
      // ***********************************************************

      // Done
      allPassed(passed, 1);  // Be sure to change the one to match
      // the number of tests you add.
      $finish;
   end

   // Initialize the clock to be 0
   initial begin
      CLK = 0;
   end

   // The following is correct if clock starts at LOW level at StartTime //
   always begin
      #`HalfClockPeriod CLK = ~CLK;
      #`HalfClockPeriod CLK = ~CLK;
      watchdog = watchdog +1;
   end

   // Kill the simulation if the watchdog hits 64K cycles
   always @*
     if (watchdog == 16'hFF)
       begin
          $display("Watchdog Timer Expired.");
          $finish;
       end


endmodule

Lab09/singlecycle.vcd
$date
	Fri Dec  1 00:18:14 2023
$end
$version
	Icarus Verilog
$end
$timescale
	1ps
$end
$scope module SingleCycleProcTest_v $end
$var wire 64 ! currentPC [63:0] $end
$var wire 64 " MemtoRegOut [63:0] $end
$var reg 1 # CLK $end
$var reg 1 $ Reset_L $end
$var reg 8 % passed [7:0] $end
$var reg 64 & startPC [63:0] $end
$var reg 16 ' watchdog [15:0] $end
$scope module uut $end
$var wire 1 # CLK $end
$var wire 1 $ resetl $end
$var wire 64 ( startpc [63:0] $end
$var wire 1 ) zero $end
$var wire 1 * uncond_branch $end
$var wire 2 + signop [1:0] $end
$var wire 5 , rn [4:0] $end
$var wire 5 - rm [4:0] $end
$var wire 1 . regwrite $end
$var wire 64 / regoutB [63:0] $end
$var wire 64 0 regoutA [63:0] $end
$var wire 1 1 reg2loc $end
$var wire 5 2 rd [4:0] $end
$var wire 11 3 opcode [10:0] $end
$var wire 64 4 nextpc [63:0] $end
$var wire 1 5 memwrite $end
$var wire 1 6 memread $end
$var wire 1 7 mem2reg $end
$var wire 32 8 instruction [31:0] $end
$var wire 64 9 extmem [63:0] $end
$var wire 64 : extimm [63:0] $end
$var wire 1 ; branch $end
$var wire 1 < alusrc $end
$var wire 64 = aluout [63:0] $end
$var wire 4 > aluctrl [3:0] $end
$var wire 64 ? MuxToAlu [63:0] $end
$var wire 64 @ MemtoRegOut [63:0] $end
$var reg 64 A currentpc [63:0] $end
$scope module NPC $end
$var wire 64 B CurrentPC [63:0] $end
$var wire 1 * Uncondbranch $end
$var wire 64 C Tmpimm [63:0] $end
$var wire 64 D SignExtImm64 [63:0] $end
$var wire 1 ; Branch $end
$var wire 1 ) ALUZero $end
$var reg 64 E NextPC [63:0] $end
$upscope $end
$scope module SignExtend $end
$var wire 26 F Imm26 [25:0] $end
$var wire 2 G Ctrl [1:0] $end
$var reg 64 H BusImm [63:0] $end
$var reg 1 I extBit $end
$upscope $end
$scope module alu $end
$var wire 64 J BusB [63:0] $end
$var wire 1 ) Zero $end
$var wire 64 K BusA [63:0] $end
$var wire 4 L ALUCtrl [3:0] $end
$var reg 64 M BusW [63:0] $end
$upscope $end
$scope module control $end
$var wire 11 N opcode [10:0] $end
$var reg 4 O aluop [3:0] $end
$var reg 1 < alusrc $end
$var reg 1 ; branch $end
$var reg 1 7 mem2reg $end
$var reg 1 6 memread $end
$var reg 1 5 memwrite $end
$var reg 1 1 reg2loc $end
$var reg 1 . regwrite $end
$var reg 2 P signop [1:0] $end
$var reg 1 * uncond_branch $end
$upscope $end
$scope module dmem $end
$var wire 64 Q Address [63:0] $end
$var wire 1 # Clock $end
$var wire 1 6 MemoryRead $end
$var wire 1 5 MemoryWrite $end
$var wire 64 R WriteData [63:0] $end
$var reg 64 S ReadData [63:0] $end
$scope task initset $end
$var reg 64 T addr [63:0] $end
$var reg 64 U data [63:0] $end
$upscope $end
$upscope $end
$scope module imem $end
$var wire 64 V Address [63:0] $end
$var reg 32 W Data [31:0] $end
$upscope $end
$scope module regFile $end
$var wire 64 X BusW [63:0] $end
$var wire 1 # Clk $end
$var wire 5 Y RA [4:0] $end
$var wire 5 Z RB [4:0] $end
$var wire 5 [ RW [4:0] $end
$var wire 1 . RegWr $end
$var wire 64 \ BusB [63:0] $end
$var wire 64 ] BusA [63:0] $end
$upscope $end
$upscope $end
$scope task allPassed $end
$var reg 8 ^ numTests [7:0] $end
$var reg 8 _ passed [7:0] $end
$upscope $end
$scope task passTest $end
$var reg 64 ` actualOut [63:0] $end
$var reg 64 a expectedOut [63:0] $end
$var reg 8 b passed [7:0] $end
$var reg 257 c testType [256:0] $end
$upscope $end
$upscope $end
$enddefinitions $end
#0
$dumpvars
bx c
bx b
bx a
bx `
bx _
bx ^
bx ]
bx \
bx [
bx Z
bx Y
bx X
bx W
bx V
b0 U
b100000 T
bx S
bx R
bx Q
bx P
bx O
bx N
bx M
bx L
bx K
bx J
xI
bx H
bx G
bx F
bx E
bx D
bx00 C
bx B
bx A
bx @
bx ?
bx >
bx =
x<
x;
bx :
bx 9
bx 8
x7
x6
x5
bx 4
bx 3
bx 2
x1
bx 0
bx /
x.
bx -
bx ,
bx +
x*
x)
b0 (
b0 '
b0 &
b0 %
1$
0#
bx "
bx !
$end
#2000
b0xxxxxxxxxxxxxxxxxxxxxxxxxxxxxxxx /
b0xxxxxxxxxxxxxxxxxxxxxxxxxxxxxxxx R
b0xxxxxxxxxxxxxxxxxxxxxxxxxxxxxxxx \
b0xxxxxxxxxxxxxxxxxxxxxxxxxxxxxxxx 0
b0xxxxxxxxxxxxxxxxxxxxxxxxxxxxxxxx K
b0xxxxxxxxxxxxxxxxxxxxxxxxxxxxxxxx ]
#60000
1#
#120000
b1 '
0#
#121000
0$
#180000
1#
#240000
b10 '
0#
#243000
0)
b10010001 "
b10010001 @
b10010001 X
b10010001 =
b10010001 M
b10010001 Q
b1001000100 C
b10010001 ?
b10010001 J
b10010001 :
b10010001 D
b10010001 H
0I
b0 +
b0 G
b0 P
b111 >
b111 L
b111 O
0*
0;
05
06
1.
07
1<
01
b100 4
b100 E
b10 ,
b10 Z
b10100000100100011010001001 F
b11010010100 3
b11010010100 N
b10100 -
b10100 Y
b1001 2
b1001 [
b11010010100000100100011010001001 8
b11010010100000100100011010001001 W
b0 !
b0 A
b0 B
b0 V
#300000
1$
1#
#360000
b11 '
0#
#363000
b1000 4
b1000 E
b110 "
b110 @
b110 X
b110 =
b110 M
b110 Q
b11000 C
b110 ?
b110 J
b110 :
b110 D
b110 H
b0 ,
b0 Z
b10100000000001100000001011 F
b0 -
b0 Y
b1011 2
b1011 [
b11010010100000000001100000001011 8
b11010010100000000001100000001011 W
b100 !
b100 A
b100 B
b100 V
#420000
1#
#480000
b100 '
0#
#483000
bx +
bx G
bx P
bx >
bx L
bx O
0.
17
x<
x1
b1100 4
b1100 E
bx "
bx @
bx X
b101001000000 =
b101001000000 M
b101001000000 Q
b10100100000000 C
b0xxxxxxxxxxxxxxxxxxxxxxxxxxxxxxxx ?
b0xxxxxxxxxxxxxxxxxxxxxxxxxxxxxxxx J
b101001000000 :
b101001000000 D
b101001000000 H
b1001 ,
b1001 Z
b11011010010000000101101001 F
b11010011011 3
b11010011011 N
b1011 -
b1011 Y
b1001 2
b1001 [
b11010011011010010000000101101001 8
b11010011011010010000000101101001 W
b1000 !
b1000 A
b1000 B
b1000 V
#485000
b0x0x0xx0x000x ?
b0x0x0xx0x000x J
b10010001 /
b10010001 R
b10010001 \
b110 0
b110 K
b110 ]
#540000
1#
#600000
b101 '
0#
#603000
b1010110011 =
b1010110011 M
b1010110011 Q
b101011001100 C
b1010110011 :
b1010110011 D
b1010110011 H
b1010110011 "
b1010110011 @
b1010110011 X
b1010110011 ?
b1010110011 J
b0 +
b0 G
b0 P
b111 >
b111 L
b111 O
1.
07
1<
01
b10000 4
b10000 E
b1010 ,
b1010 Z
b10100010101100111100001010 F
b11010010100 3
b11010010100 N
b11000 -
b11000 Y
b1010 2
b1010 [
b11010010100010101100111100001010 8
b11010010100010101100111100001010 W
b1100 !
b1100 A
b1100 B
b1100 V
#605000
b0xxxxxxxxxxxxxxxxxxxxxxxxxxxxxxxx /
b0xxxxxxxxxxxxxxxxxxxxxxxxxxxxxxxx R
b0xxxxxxxxxxxxxxxxxxxxxxxxxxxxxxxx \
b0xxxxxxxxxxxxxxxxxxxxxxxxxxxxxxxx 0
b0xxxxxxxxxxxxxxxxxxxxxxxxxxxxxxxx K
b0xxxxxxxxxxxxxxxxxxxxxxxxxxxxxxxx ]
#660000
1#
#720000
b110 '
0#
#723000
b10100 4
b10100 E
b1010000000 "
b1010000000 @
b1010000000 X
b1010000000 =
b1010000000 M
b1010000000 Q
b101000000000 C
b1010000000 ?
b1010000000 J
b1010000000 :
b1010000000 D
b1010000000 H
b10100010100000000101101010 F
b1011 -
b1011 Y
b11010010100010100000000101101010 8
b11010010100010100000000101101010 W
b10000 !
b10000 A
b10000 B
b10000 V
#725000
b110 0
b110 K
b110 ]
b1010110011 /
b1010110011 R
b1010110011 \
#780000
1#
#840000
b111 '
0#
#843000
bx +
bx G
bx P
bx >
bx L
bx O
0.
17
x<
x1
b11000 4
b11000 E
bx "
bx @
bx X
b10110000101 =
b10110000101 M
b10110000101 Q
b1011000010100 C
b0xxx10xx0xx1 ?
b0xxx10xx0xx1 J
b10110000101 :
b10110000101 D
b10110000101 H
bx10 ,
bx10 Z
b1000101100001010100101010 F
b1000 3
b1000 N
b1001 -
b1001 Y
b1000101100001010100101010 8
b1000101100001010100101010 W
b10100 !
b10100 A
b10100 B
b10100 V
#845000
b0xxxxxxxxxxxxxxxxxxxxxxxxxxxxxxxx ?
b0xxxxxxxxxxxxxxxxxxxxxxxxxxxxxxxx J
b10010001 0
b10010001 K
b10010001 ]
b0xxxxxxxxxxxxxxxxxxxxxxxxxxxxxxxx /
b0xxxxxxxxxxxxxxxxxxxxxxxxxxxxxxxx R
b0xxxxxxxxxxxxxxxxxxxxxxxxxxxxxxxx \
#900000
1#
#960000
b1000 '
0#
