Lab09/DataMemory.v
`timescale 1ns / 1ps

`define SIZE 1024

module DataMemory(ReadData , Address , WriteData , MemoryRead , MemoryWrite , Clock);
   input [63:0]      WriteData;
   input [63:0]      Address;
   input             Clock, MemoryRead, MemoryWrite;
   output reg [63:0] ReadData;

   reg [7:0] 	     memBank [`SIZE-1:0];


   // This task is used to write arbitrary data to the Data Memory by
   // the intialization block.
   task initset;
      input [63:0] addr;
      input [63:0] data;
      begin
	 memBank[addr] =  data[63:56] ; // Big-endian for the win...
	 memBank[addr+1] =  data[55:48];
	 memBank[addr+2] =  data[47:40];
	 memBank[addr+3] =  data[39:32];
	 memBank[addr+4] =  data[31:24];
	 memBank[addr+5] =  data[23:16];
	 memBank[addr+6] =  data[15:8];
	 memBank[addr+7] =  data[7:0];
      end
   endtask


   initial
     begin
        // preseting some data in the data memory used by test #1

        // Address 0x0 gets 0x1
        initset( 64'h0,  64'h1);  //Counter variable
        initset( 64'h8,  64'ha);  //Part of mask
        initset( 64'h10, 64'h5);  //Other part of mask
        initset( 64'h18, 64'h0ffbea7deadbeeff); //big constant
        initset( 64'h20, 64'h0); //clearing space

        // Add any data you need for your tests here.
        initset( 64'h22, 64'h123456789abcdef0)

     end

   // This always block reads the data memory and places a double word
   // on the ReadData bus.
   always @(posedge Clock)
     begin
        if(MemoryRead)
          begin
             ReadData[63:56] <=  memBank[Address];
             ReadData[55:48] <=  memBank[Address+1];
             ReadData[47:40] <=  memBank[Address+2];
             ReadData[39:32] <=  memBank[Address+3];
             ReadData[31:24] <=  memBank[Address+4];
             ReadData[23:16] <=  memBank[Address+5];
             ReadData[15:8] <=  memBank[Address+6];
             ReadData[7:0] <=  memBank[Address+7];
          end
     end

   // This always block takes data from the WriteData bus and writes
   // it into the DataMemory.
   always @(posedge Clock)
     begin
        if(MemoryWrite)
          begin
             memBank[Address] <= #3 WriteData[63:56] ;
             memBank[Address+1] <= #3 WriteData[55:48];
             memBank[Address+2] <= #3 WriteData[47:40];
             memBank[Address+3] <= #3 WriteData[39:32];
             memBank[Address+4] <= #3 WriteData[31:24];
             memBank[Address+5] <= #3 WriteData[23:16];
             memBank[Address+6] <= #3 WriteData[15:8];
             memBank[Address+7] <= #3 WriteData[7:0];
             // Could be useful for debugging:
             // $display("Writing Address:%h Data:%h",Address, WriteData);
          end
     end
     //$display("Dmem:%h",ReadData);
endmodule

Lab09/ALU.v
`define AND   4'b0000
`define OR    4'b0001
`define ADD   4'b0010
`define SUB   4'b0110
`define PassB 4'b0111

module ALU(BusW, BusA, BusB, ALUCtrl, Zero);
    
    output  [63:0] BusW;
    input   [63:0] BusA, BusB;
    input   [3:0] ALUCtrl;
    output  Zero;
    
    reg     [63:0] BusW;
    
    always @(ALUCtrl or BusA or BusB) begin
        case(ALUCtrl)
            4'b0000: begin /* AND */
                BusW = BusA & BusB;
            end
            4'b0001: begin /* OR */
				BusW = BusA | BusB;
			end
			4'b0010: begin /*ADD */
				BusW = BusA + BusB;
			end
			4'b0110: begin /* SUB */
				BusW = BusA - BusB;
			end
			4'b0111: begin /*PassB */
				BusW = BusB;
			end
			
        endcase
        //$display("BusW:%h", BusW);
    end
	
    assign Zero = (BusW ? 0 : 1);
endmodule

Lab09/SignExtender.v
module SignExtender(BusImm, Imm26, Ctrl); 
   output reg [63:0] BusImm; 
   input [25:0]  Imm26;
   input [1:0]	Ctrl; 
   
   reg extBit; 
   always @(Ctrl, Imm26)
   begin
		case(Ctrl)
			2'b00: /* I-Type instructions */
				begin
				extBit = 0;
			    BusImm = {{52{extBit}}, Imm26[21:10]};
			    end
			2'b01: /* D-Type instructions */
				begin
				extBit = Imm26[20];
				BusImm = {{55{extBit}}, Imm26[20:12]};
				end
			2'b10: /* B instructions */
				begin
				extBit = Imm26[25];
				BusImm = {{38{extBit}}, Imm26[25:0]};
				end
			2'b11: /* CBZ instructions */
				begin
				extBit = Imm26[23]; 
				BusImm = {{45{extBit}}, Imm26[23:5]};
				end
		endcase
	end
endmodule

Lab09/RegisterFile.v
`timescale 1ns / 1ps

module RegisterFile(BusA, BusB, BusW, RA, RB, RW, RegWr, Clk);
    output [63:0] BusA;
    output [63:0] BusB;
    input [63:0] BusW;
    input [4:0] RW;
    input [4:0] RA;
    input [4:0] RB;
    input RegWr;
    input Clk;
    reg [31:0] registers [63:0];
	
	
	assign #2 BusA = (RA==31) ? 0 : registers[RA];
	assign #2 BusB = (RB==31) ? 0 : registers[RB];
     
    always @ (negedge Clk) begin
        if(RegWr && (RW != 31))
            registers[RW] <= #3 BusW;
            registers[31] <= #3 0; 
        $display("Ra:%d", RA);    
        $display("Rb:%d", RB);
        $display("BusA:%h", BusA);
        $display("BusB:%h", BusB);
        $display("BusW:%h", BusW);
    end
    
    
	

    

endmodule

Lab09/SingleCycleControl.v
`define OPCODE_ANDREG 11'b?0001010???
`define OPCODE_ORRREG 11'b?0101010???
`define OPCODE_ADDREG 11'b?0?01011???
`define OPCODE_SUBREG 11'b?1?01011???

`define OPCODE_ADDIMM 11'b?0?10001???
`define OPCODE_SUBIMM 11'b?1?10001???

`define OPCODE_MOVZ   11'b110100101??

`define OPCODE_B      11'b?00101?????
`define OPCODE_CBZ    11'b?011010????

`define OPCODE_LDUR   11'b11111000010
`define OPCODE_STUR   11'b??111000000
`timescale 1ns / 1ps
module control(
    output reg reg2loc,
    output reg alusrc,
    output reg mem2reg,
    output reg regwrite,
    output reg memread,
    output reg memwrite,
    output reg branch,
    output reg uncond_branch,
    output reg [3:0] aluop,
    output reg [1:0] signop,
    input [10:0] opcode
);

always @(*)
begin
    casez (opcode)
    
    `OPCODE_ANDREG : 
	begin // AND
	    reg2loc       <= 1'b0;
            alusrc        <= 1'b0;
            mem2reg       <= 1'b0;
            regwrite      <= 1'b1;
            memread       <= 1'b0;
            memwrite      <= 1'b0;
            branch        <= 1'b0;
            uncond_branch <= 1'b0;
            aluop         <= 4'b0000;
            signop        <= 2'bxx;
	end
		
    `OPCODE_ORRREG : // ORR
	begin
	    reg2loc       <= 1'b0;
            alusrc        <= 1'b0;
            mem2reg       <= 1'b0;
            regwrite      <= 1'b1;
            memread       <= 1'b0;
            memwrite      <= 1'b0;
            branch        <= 1'b0;
            uncond_branch <= 1'b0;
            aluop         <= 4'b0001;
            signop        <= 2'bxx;
	end
		
    `OPCODE_ADDREG : // ADDR
	begin
	    reg2loc       <= 1'b0;
            alusrc        <= 1'b0;
            mem2reg       <= 1'b0;
            regwrite      <= 1'b1;
            memread       <= 1'b0;
            memwrite      <= 1'b0;
            branch        <= 1'b0;
            uncond_branch <= 1'b0;
            aluop         <= 4'b0010;
            signop        <= 2'bxx;
	end
		
    `OPCODE_SUBREG : // SUBR
	begin
	    reg2loc       <= 1'b0;
            alusrc        <= 1'b0;
            mem2reg       <= 1'b0;
            regwrite      <= 1'b1;
            memread       <= 1'b0;
            memwrite      <= 1'b0;
            branch        <= 1'b0;
            uncond_branch <= 1'b0;
            aluop         <= 4'b0110;
            signop        <= 2'bxx;
        end
		
    `OPCODE_ADDIMM : // ADDI			
	begin
		    reg2loc       <= 1'bx;
            alusrc        <= 1'b1;
            mem2reg       <= 1'b0;
            regwrite      <= 1'b1;
            memread       <= 1'b0;
            memwrite      <= 1'b0;
            branch        <= 1'b0;
            uncond_branch <= 1'b0;
            aluop         <= 4'b0010;
            signop        <= 2'b00;
		end
		
    `OPCODE_SUBIMM : // SUBI			
	begin
	    reg2loc       <= 1'bx;
            alusrc        <= 1'b1;
            mem2reg       <= 1'b0;
            regwrite      <= 1'b1;
            memread       <= 1'b0;
            memwrite      <= 1'b0;
            branch        <= 1'b0;
            uncond_branch <= 1'b0;
            aluop         <= 4'b0110;
            signop        <= 2'b00;
	end
		
		
    `OPCODE_B : // B
	begin
	    reg2loc       <= 1'bx;
            alusrc        <= 1'b0;
            mem2reg       <= 1'bx;
            regwrite      <= 1'b0;
            memread       <= 1'b0;
            memwrite      <= 1'b0;
            branch        <= 1'b0;
            uncond_branch <= 1'b1;
            aluop         <= 4'b0111;
            signop        <= 2'b10;
	end
		
    `OPCODE_CBZ : // CBZ
	begin
	    reg2loc       <= 1'b1;
            alusrc        <= 1'b0;
            mem2reg       <= 1'bx;
            regwrite      <= 1'b0;
            memread       <= 1'b0;
            memwrite      <= 1'b0;
            branch        <= 1'b1;
            uncond_branch <= 1'b0;
            aluop         <= 4'b0111;
            signop        <= 2'b11;
	end
		
    `OPCODE_LDUR : // LDUR
	  begin
	    reg2loc       <= 1'bx;
            alusrc        <= 1'b1;
            mem2reg       <= 1'b1;
            regwrite      <= 1'b1;
            memread       <= 1'b1;
            memwrite      <= 1'b0;
            branch        <= 1'b0;
            uncond_branch <= 1'bx;
            aluop         <= 4'b0010;
            signop        <= 2'b01;
	  end
		
    `OPCODE_STUR : //STUR
	  begin
	    reg2loc       <= 1'b1;
            alusrc        <= 1'b1;
            mem2reg       <= 1'bx;
            regwrite      <= 1'b0;
            memread       <= 1'b0;
            memwrite      <= 1'b1;
            branch        <= 1'b0;
            uncond_branch <= 1'b0;
            aluop         <= 4'b0010;
            signop        <= 2'b01;
	  end

        default:
        begin
            reg2loc       <= 1'bx;
            alusrc        <= 1'bx;
            mem2reg       <= 1'bx;
            regwrite      <= 1'b0;
            memread       <= 1'b0;
            memwrite      <= 1'b0;
            branch        <= 1'b0;
            uncond_branch <= 1'b0;
            aluop         <= 4'bxxxx;
            signop        <= 2'bxx;
        end
        
    endcase
    //$display("mem2reg:%h", mem2reg);
end

endmodule

Lab09/NextPClogic.v
`timescale 1ns / 1ps
module NextPClogic(NextPC, CurrentPC, SignExtImm64, Branch, ALUZero, Uncondbranch); 
   input [63:0] CurrentPC, SignExtImm64; 
   input 	Branch, ALUZero, Uncondbranch; 
   output reg [63:0] NextPC; 
   wire [63:0] Tmpimm;
	assign Tmpimm = SignExtImm64 << 2;
   always @(*)
		begin
		if(Uncondbranch) begin
			NextPC <= CurrentPC + Tmpimm;
		end else if (Branch) begin
			if (ALUZero) begin
				NextPC <= CurrentPC + Tmpimm;
			end else begin
				NextPC <= CurrentPC + 4;
			end
		end else begin
			NextPC <= CurrentPC + 4;
		end
	end

endmodule

Lab09/InstructionMemory.v
`timescale 1ns / 1ps
/*
 * Module: InstructionMemory
 *
 * Implements read-only instruction memory
 * 
 */
module InstructionMemory(Data, Address);
   parameter T_rd = 20;
   parameter MemSize = 40;
   
   output [31:0] Data;
   input [63:0]  Address;
   reg [31:0] 	 Data;
   
   /*
    * ECEN 350 Processor Test Functions
    * Texas A&M University
    */
   
   always @ (Address) begin

      case(Address)

	/* Test Program 1:
	 * Program loads constants from the data memory. Uses these constants to test
	 * the following instructions: LDUR, ORR, AND, CBZ, ADD, SUB, STUR and B.
	 * 
	 * Assembly code for test:
	 * 
	 * 0: LDUR X9, [XZR, 0x0]    //Load 1 into x9
	 * 4: LDUR X10, [XZR, 0x8]   //Load a into x10
	 * 8: LDUR X11, [XZR, 0x10]  //Load 5 into x11
	 * C: LDUR X12, [XZR, 0x18]  //Load big constant into x12
	 * 10: LDUR X13, [XZR, 0x20]  //load a 0 into X13
	 * 
	 * 14: ORR X10, X10, X11  //Create mask of 0xf
	 * 18: AND X12, X12, X10  //Mask off low order bits of big constant
	 * 
	 * loop:
	 * 1C: CBZ X12, end  //while X12 is not 0
	 * 20: ADD X13, X13, X9  //Increment counter in X13
	 * 24: SUB X12, X12, X9  //Decrement remainder of big constant in X12
	 * 28: B loop  //Repeat till X12 is 0
	 * 2C: STUR X13, [XZR, 0x20]  //store back the counter value into the memory location 0x20
	 */
	

	63'h000: Data = 32'hF84003E9;
	63'h004: Data = 32'hF84083EA;
	63'h008: Data = 32'hF84103EB;
	63'h00c: Data = 32'hF84183EC;
	63'h010: Data = 32'hF84203ED;
	63'h014: Data = 32'hAA0B014A;
	63'h018: Data = 32'h8A0A018C;
	63'h01c: Data = 32'hB400008C;
	63'h020: Data = 32'h8B0901AD;
	63'h024: Data = 32'hCB09018C;
	63'h028: Data = 32'h17FFFFFD;
	63'h02c: Data = 32'hF80203ED;
	63'h030: Data = 32'hF84203ED;  //One last load to place stored value on memdbus for test checking.

	/* Add code for your tests here */

	
	default: Data = 32'hXXXXXXXX;
      endcase
	
   end
endmodule

Lab09/SingleCycleProc.v

module singlecycle(
		   input 	     resetl,
		   input [63:0]      startpc,
		   output reg [63:0] currentpc,
		   output [63:0]     MemtoRegOut,  // this should be
						   // attached to the
						   // output of the
						   // MemtoReg Mux
		   input 	     CLK
		   );

   // Next PC connections
   wire [63:0] 			     nextpc;       // The next PC, to be updated on clock cycle

   // Instruction Memory connections
   wire [31:0] 			     instruction;  // The current instruction

   // Parts of instruction
   wire [4:0] 			     rd;            // The destination register
   wire [4:0] 			     rm;            // Operand 1
   wire [4:0] 			     rn;            // Operand 2
   wire [10:0] 			     opcode;
   
   //Added wires for MUXes
   wire [63:0]				 MuxToAlu;

   // Control wires
   wire 			     reg2loc;
   wire 			     alusrc;
   wire 			     mem2reg;
   wire 			     regwrite;
   wire 			     memread;
   wire 			     memwrite;
   wire 			     branch;
   wire 			     uncond_branch;
   wire [3:0] 			     aluctrl;
   wire [1:0] 			     signop;

   // Register file connections
   wire [63:0] 			     regoutA;     // Output A
   wire [63:0] 			     regoutB;     // Output B
   // ALU connections
   wire [63:0] 			     aluout;
   wire 			     zero;
   //2nd ALU
   wire [63:0]               Mux2Alu;

   // Sign Extender connections
   wire [63:0] 			     extimm;
   
   //Data Memory connection
   wire [63:0]				extmem;
   
   //Wire
   wire 					andout;
   wire						orout;
   wire[63:0]				ALUout2;
		

   // PC update logic




   InstructionMemory imem(
			  .Data(instruction),
			  .Address(currentpc)
			  );
			  
			  
	NextPClogic NPC(
		.NextPC(nextpc),
		.CurrentPC(currentpc),
		.SignExtImm64(extimm),
		.Branch(branch),
		.ALUZero(zero),
		.Uncondbranch(uncond_branch)
	);
	   always @(negedge CLK)
     begin
        if (resetl)
          currentpc <= #3 nextpc;
        else
          currentpc <= #3 startpc;
     end


   control control(
		   .reg2loc(reg2loc),
		   .alusrc(alusrc),
		   .mem2reg(mem2reg),
		   .regwrite(regwrite),
		   .memread(memread),
		   .memwrite(memwrite),
		   .branch(branch),
		   .uncond_branch(uncond_branch),
		   .aluop(aluctrl),
		   .signop(signop),
		   .opcode(opcode)
		   );
		   
   // Parts of instruction
   assign #2 rd = instruction[4:0];
   assign #2 rm = instruction[9:5];
   assign #2 rn = reg2loc ? instruction[4:0] : instruction[20:16];
   assign #2 opcode = instruction[31:21];
		   
	RegisterFile regFile(
			.RA(rm),
			.RB(rn),
			.RW(rd),
			.BusW(MemtoRegOut),
			.RegWr(regwrite),
			.Clk(CLK),
			.BusA(regoutA),
			.BusB(regoutB)
			);
			
			
	SignExtender SignExtend(
			.Imm26(instruction[25:0]),
			.BusImm(extimm),
			.Ctrl(signop)
			);
			
	//MuxToALU wire
	assign #2 MuxToAlu = alusrc ? extimm : regoutB;
			
	ALU ArithmeticUnit(
			.BusA(regoutA),
			.BusB(Mux2Alu),
			.BusW(aluout),
			.ALUCtrl(aluctrl),
			.Zero(zero)
			);
			
	DataMemory dmem(
		.ReadData(extmem),
		.Address(aluout),
		.WriteData(regoutB),
		.MemoryRead(memread),
		.MemoryWrite(memwrite),
		.Clock(CLK)
		);
			
   //Mux
   assign #2 MemtoRegOut = mem2reg ?  extmem : aluout; //Added
	
	


   /*
    * Connect the remaining datapath elements below.
    * Do not forget any additional multiplexers that may be required.
    */



endmodule

Lab09/SingleCycleProcTest.v
`timescale 1ns / 1ps

`define STRLEN 32
`define HalfClockPeriod 60
`define ClockPeriod `HalfClockPeriod * 2

module SingleCycleProcTest_v;

   initial
     begin
        $dumpfile("singlecycle.vcd");
        $dumpvars;
     end

   // These tasks are used to check if a given test has passed and
   // confirm that all tests passed.
   task passTest;
      input [63:0] actualOut, expectedOut;
      input [`STRLEN*8:0] testType;
      inout [7:0] 	  passed;

      if(actualOut == expectedOut) begin $display ("%s passed", testType); passed = passed + 1; end
      else $display ("%s failed: 0x%x should be 0x%x", testType, actualOut, expectedOut);
   endtask

   task allPassed;
      input [7:0] passed;
      input [7:0] numTests;

      if(passed == numTests) $display ("All tests passed");
      else $display("Some tests failed: %d of %d passed", passed, numTests);
   endtask

   // Inputs
   reg 		  CLK;
   reg 		  Reset_L;
   reg [63:0] 	  startPC;
   reg [7:0] 	  passed;
   reg [15:0] 	  watchdog;

   // Outputs
   wire [63:0] 	  MemtoRegOut;
   wire [63:0] 	  currentPC;
   

   // Instantiate the Unit Under Test (UUT)
   singlecycle uut (
		    .CLK(CLK),
		    .resetl(Reset_L),
		    .startpc(startPC),
		    .currentpc(currentPC),
		    .MemtoRegOut(MemtoRegOut)
		    );

   initial begin
      // Initialize Inputs
      Reset_L = 1;
      startPC = 0;
      passed = 0;

      // Initialize Watchdog timer
      watchdog = 0;

      // Wait for global reset
      #(1 * `ClockPeriod);

      // Program 1
      #1
        Reset_L = 0; startPC =0;
      @(posedge CLK);
      @(negedge CLK);
      @(posedge CLK);
      Reset_L = 1;

      // ***********************************************************
      // This while loop will continue cycling the processor until the
      // PC reaches the final instruction in the first test.  If the
      // program forms an infinite loop, never reaching the end, the
      // watchdog timer will kick in and kill simulation after 64K
      // cycles.
      // ***********************************************************
		
      while (currentPC < 64'h30)
        begin
	   @(posedge CLK);  
		   $display("CurrentPC:%h",currentPC);
           //$display("MemtoReg:%h",MemtoRegOut);
           $display("regs:%h", );
	   @(negedge CLK);

        end
      
      passTest(MemtoRegOut, 64'hF, "Results of Program 1", passed);

      // ***********************************************************
      // Add your new tests here
      // ***********************************************************

      // Done
      allPassed(passed, 2);   // Be sure to change the one to match
      // the number of tests you add.
      $finish;
   end

   // Initialize the clock to be 0
   initial begin
      CLK = 0;
   end

   // The following is correct if clock starts at LOW level at StartTime //
   always begin
      #`HalfClockPeriod CLK = ~CLK;
      #`HalfClockPeriod CLK = ~CLK;
      watchdog = watchdog +1;
   end

   // Kill the simulation if the watchdog hits 64K cycles
   always @*
     if (watchdog == 16'hFF)
       begin
          $display("Watchdog Timer Expired.");
          $finish;
       end


endmodule

Lab09/singlecycle.vcd
$date
	Wed Nov 29 03:38:31 2023
$end
$version
	Icarus Verilog
$end
$timescale
	1ps
$end
$scope module SingleCycleProcTest_v $end
$var wire 64 ! currentPC [63:0] $end
$var wire 64 " MemtoRegOut [63:0] $end
$var reg 1 # CLK $end
$var reg 1 $ Reset_L $end
$var reg 8 % passed [7:0] $end
$var reg 64 & startPC [63:0] $end
$var reg 16 ' watchdog [15:0] $end
$scope module uut $end
$var wire 1 # CLK $end
$var wire 64 ( Mux2Alu [63:0] $end
$var wire 1 $ resetl $end
$var wire 64 ) startpc [63:0] $end
$var wire 1 * zero $end
$var wire 1 + uncond_branch $end
$var wire 2 , signop [1:0] $end
$var wire 5 - rn [4:0] $end
$var wire 5 . rm [4:0] $end
$var wire 1 / regwrite $end
$var wire 64 0 regoutB [63:0] $end
$var wire 64 1 regoutA [63:0] $end
$var wire 1 2 reg2loc $end
$var wire 5 3 rd [4:0] $end
$var wire 11 4 opcode [10:0] $end
$var wire 64 5 nextpc [63:0] $end
$var wire 1 6 memwrite $end
$var wire 1 7 memread $end
$var wire 1 8 mem2reg $end
$var wire 32 9 instruction [31:0] $end
$var wire 64 : extmem [63:0] $end
$var wire 64 ; extimm [63:0] $end
$var wire 1 < branch $end
$var wire 1 = alusrc $end
$var wire 64 > aluout [63:0] $end
$var wire 4 ? aluctrl [3:0] $end
$var wire 64 @ MuxToAlu [63:0] $end
$var wire 64 A MemtoRegOut [63:0] $end
$var reg 64 B currentpc [63:0] $end
$scope module ArithmeticUnit $end
$var wire 64 C BusB [63:0] $end
$var wire 1 * Zero $end
$var wire 64 D BusA [63:0] $end
$var wire 4 E ALUCtrl [3:0] $end
$var reg 64 F BusW [63:0] $end
$upscope $end
$scope module NPC $end
$var wire 1 * ALUZero $end
$var wire 64 G CurrentPC [63:0] $end
$var wire 1 + Uncondbranch $end
$var wire 64 H Tmpimm [63:0] $end
$var wire 64 I SignExtImm64 [63:0] $end
$var wire 1 < Branch $end
$var reg 64 J NextPC [63:0] $end
$upscope $end
$scope module SignExtend $end
$var wire 26 K Imm26 [25:0] $end
$var wire 2 L Ctrl [1:0] $end
$var reg 64 M BusImm [63:0] $end
$var reg 1 N extBit $end
$upscope $end
$scope module control $end
$var wire 11 O opcode [10:0] $end
$var reg 4 P aluop [3:0] $end
$var reg 1 = alusrc $end
$var reg 1 < branch $end
$var reg 1 8 mem2reg $end
$var reg 1 7 memread $end
$var reg 1 6 memwrite $end
$var reg 1 2 reg2loc $end
$var reg 1 / regwrite $end
$var reg 2 Q signop [1:0] $end
$var reg 1 + uncond_branch $end
$upscope $end
$scope module dmem $end
$var wire 64 R Address [63:0] $end
$var wire 1 # Clock $end
$var wire 1 7 MemoryRead $end
$var wire 1 6 MemoryWrite $end
$var wire 64 S WriteData [63:0] $end
$var reg 64 T ReadData [63:0] $end
$scope task initset $end
$var reg 64 U addr [63:0] $end
$var reg 64 V data [63:0] $end
$upscope $end
$upscope $end
$scope module imem $end
$var wire 64 W Address [63:0] $end
$var reg 32 X Data [31:0] $end
$upscope $end
$scope module regFile $end
$var wire 64 Y BusW [63:0] $end
$var wire 1 # Clk $end
$var wire 5 Z RA [4:0] $end
$var wire 5 [ RB [4:0] $end
$var wire 5 \ RW [4:0] $end
$var wire 1 / RegWr $end
$var wire 64 ] BusB [63:0] $end
$var wire 64 ^ BusA [63:0] $end
$upscope $end
$upscope $end
$scope task allPassed $end
$var reg 8 _ numTests [7:0] $end
$var reg 8 ` passed [7:0] $end
$upscope $end
$scope task passTest $end
$var reg 64 a actualOut [63:0] $end
$var reg 64 b expectedOut [63:0] $end
$var reg 8 c passed [7:0] $end
$var reg 257 d testType [256:0] $end
$upscope $end
$upscope $end
$enddefinitions $end
#0
$dumpvars
bx d
bx c
bx b
bx a
bx `
bx _
bx ^
bx ]
bx \
bx [
bx Z
bx Y
bx X
bx W
b0 V
b100000 U
bx T
bx S
bx R
bx Q
bx P
bx O
xN
bx M
bx L
bx K
bx J
bx I
bx00 H
bx G
bx F
bx E
bx D
bz C
bx B
bx A
bx @
bx ?
bx >
x=
x<
bx ;
bx :
bx 9
x8
x7
x6
bx 5
bx 4
bx 3
x2
bx 1
bx 0
x/
bx .
bx -
bx ,
x+
x*
b0 )
bz (
b0 '
b0 &
b0 %
1$
0#
bx "
bx !
$end
#2000
b0xxxxxxxxxxxxxxxxxxxxxxxxxxxxxxxx 0
b0xxxxxxxxxxxxxxxxxxxxxxxxxxxxxxxx S
b0xxxxxxxxxxxxxxxxxxxxxxxxxxxxxxxx ]
b0xxxxxxxxxxxxxxxxxxxxxxxxxxxxxxxx 1
b0xxxxxxxxxxxxxxxxxxxxxxxxxxxxxxxx D
b0xxxxxxxxxxxxxxxxxxxxxxxxxxxxxxxx ^
#60000
1#
#120000
b1 '
0#
#121000
0$
#180000
1#
#240000
b10 '
0#
#243000
b100 5
b100 J
b10000000000001111101001 K
b11111000010000000000001111101001 9
b11111000010000000000001111101001 X
b0 !
b0 B
b0 G
b0 W
#245000
b0 H
b0 ;
b0 I
b0 M
0N
b1 ,
b1 L
b1 Q
b10 ?
b10 E
b10 P
0<
06
17
1/
18
1=
b0x00x -
b0x00x [
b11111000010 4
b11111000010 O
b11111 .
b11111 Z
b1001 3
b1001 \
#247000
b0 @
b0 1
b0 D
b0 ^
#300000
1$
1#
#360000
b11 '
0#
#363000
b1000 5
b1000 J
b100000 H
b1000 ;
b1000 I
b1000 M
b10000001000001111101010 K
b11111000010000001000001111101010 9
b11111000010000001000001111101010 X
b100 !
b100 B
b100 G
b100 W
#365000
b1000 @
b0x0x0 -
b0x0x0 [
b1010 3
b1010 \
#420000
1#
#480000
b100 '
0#
#483000
b1100 5
b1100 J
b1000000 H
b10000 ;
b10000 I
b10000 M
b10000010000001111101011 K
b11111000010000010000001111101011 9
b11111000010000010000001111101011 X
b1000 !
b1000 B
b1000 G
b1000 W
#485000
b10000 @
b0x0x1 -
b0x0x1 [
b1011 3
b1011 \
#540000
1#
#600000
b101 '
0#
#603000
b10000 5
b10000 J
b1100000 H
b11000 ;
b11000 I
b11000 M
b10000011000001111101100 K
b11111000010000011000001111101100 9
b11111000010000011000001111101100 X
b1100 !
b1100 B
b1100 G
b1100 W
#605000
b11000 @
b0xx0x -
b0xx0x [
b1100 3
b1100 \
#660000
1#
#720000
b110 '
0#
#723000
b10100 5
b10100 J
b10000000 H
b100000 ;
b100000 I
b100000 M
b10000100000001111101101 K
b11111000010000100000001111101101 9
b11111000010000100000001111101101 X
b10000 !
b10000 B
b10000 G
b10000 W
#725000
b100000 @
b0xxxx -
b0xxxx [
b1101 3
b1101 \
#780000
1#
#840000
b111 '
0#
#843000
b11000 5
b11000 J
b1011000000 H
b10110000 ;
b10110000 I
b10110000 M
b10000010110000000101001010 K
b10101010000010110000000101001010 9
b10101010000010110000000101001010 X
b10100 !
b10100 B
b10100 G
b10100 W
#845000
bx ,
bx L
bx Q
b1 ?
b1 E
b1 P
0+
07
08
0=
02
b10110000 @
b101x -
b101x [
b10101010000 4
b10101010000 O
b1010 .
b1010 Z
b1010 3
b1010 \
#847000
b0xxxxxxxxxxxxxxxxxxxxxxxxxxxxxxxx @
b1011 -
b1011 [
b0xxxxxxxxxxxxxxxxxxxxxxxxxxxxxxxx 1
b0xxxxxxxxxxxxxxxxxxxxxxxxxxxxxxxx D
b0xxxxxxxxxxxxxxxxxxxxxxxxxxxxxxxx ^
#900000
1#
#960000
b1000 '
0#
#963000
b11100 5
b11100 J
b10000010100000000110001100 K
b10001010000010100000000110001100 9
b10001010000010100000000110001100 X
b11000 !
b11000 B
b11000 G
b11000 W
#965000
b0xxxxxxxxxxxxxxxxxxxxxxxxxxxxxxxx >
b0xxxxxxxxxxxxxxxxxxxxxxxxxxxxxxxx F
b0xxxxxxxxxxxxxxxxxxxxxxxxxxxxxxxx R
b0 ?
b0 E
b0 P
b1010 -
b1010 [
b10001010000 4
b10001010000 O
b1100 .
b1100 Z
b1100 3
b1100 \
#967000
b0xxxxxxxxxxxxxxxxxxxxxxxxxxxxxxxx :
b0xxxxxxxxxxxxxxxxxxxxxxxxxxxxxxxx Y
#1020000
1#
#1080000
b1001 '
0#
#1083000
b100000 5
b100000 J
b10001100 K
b10110100000000000000000010001100 9
b10110100000000000000000010001100 X
b11100 !
b11100 B
b11100 G
b11100 W
#1085000
b10000 H
b100 ;
b100 I
b100 M
bz >
bz F
bz R
b11 ,
b11 L
b11 Q
b111 ?
b111 E
b111 P
1<
0/
x8
12
b0 -
b0 [
b10110100000 4
b10110100000 O
b100 .
b100 Z
#1087000
bx :
bx Y
b1100 -
b1100 [
#1140000
1#
#1200000
b1010 '
0#
#1203000
b100100 5
b100100 J
b10010000000110100 H
b100100000001101 ;
b100100000001101 I
b100100000001101 M
b11000010010000000110101101 K
b10001011000010010000000110101101 9
b10001011000010010000000110101101 X
b100000 !
b100000 B
b100000 G
b100000 W
#1205000
bx >
bx F
bx R
bx ,
bx L
bx Q
b10 ?
b10 E
b10 P
0<
1/
08
02
b1101 -
b1101 [
b10001011000 4
b10001011000 O
b1101 .
b1101 Z
b1101 3
b1101 \
#1207000
b1001 -
b1001 [
#1260000
1#
#1320000
b1011 '
0#
#1323000
b101000 5
b101000 J
b11000010010000000110001100 K
b11001011000010010000000110001100 9
b11001011000010010000000110001100 X
b100100 !
b100100 B
b100100 G
b100100 W
#1325000
b110 ?
b110 E
b110 P
b11001011000 4
b11001011000 O
b1100 .
b1100 Z
b1100 3
b1100 \
#1380000
1#
#1440000
b1100 '
0#
#1443000
b101100 5
b101100 J
b11111111111111111111111101 K
b10111111111111111111111111101 9
b10111111111111111111111111101 X
b101000 !
b101000 B
b101000 G
b101000 W
#1445000
b11100 5
b11100 J
b1111111111111111111111111111111111111111111111111111111111110100 H
b1111111111111111111111111111111111111111111111111111111111111101 ;
b1111111111111111111111111111111111111111111111111111111111111101 I
b1111111111111111111111111111111111111111111111111111111111111101 M
1N
bz >
bz F
bz R
b10 ,
b10 L
b10 Q
b111 ?
b111 E
b111 P
1+
0/
x8
x2
b11111 -
b11111 [
b10111111 4
b10111111 O
b11111 .
b11111 Z
b11101 3
b11101 \
#1447000
b111x1 -
b111x1 [
b0 0
b0 S
b0 ]
b0 1
b0 D
b0 ^
#1449000
b0xxxxxxxxxxxxxxxxxxxxxxxxxxxxxxxx 0
b0xxxxxxxxxxxxxxxxxxxxxxxxxxxxxxxx S
b0xxxxxxxxxxxxxxxxxxxxxxxxxxxxxxxx ]
b0 @
#1451000
b0xxxxxxxxxxxxxxxxxxxxxxxxxxxxxxxx @
#1500000
1#
#1560000
b1101 '
0#
#1563000
b1001001100 5
b1001001100 J
b1000110000 H
b10001100 ;
b10001100 I
b10001100 M
0N
b10001100 K
b10110100000000000000000010001100 9
b10110100000000000000000010001100 X
b11100 !
b11100 B
b11100 G
b11100 W
#1565000
b100000 5
b100000 J
b10000 H
b100 ;
b100 I
b100 M
b11 ,
b11 L
b11 Q
0+
1<
12
b0xx00 -
b0xx00 [
b10110100000 4
b10110100000 O
b100 .
b100 Z
b1100 3
b1100 \
#1567000
b1100 -
b1100 [
b0xxxxxxxxxxxxxxxxxxxxxxxxxxxxxxxx 1
b0xxxxxxxxxxxxxxxxxxxxxxxxxxxxxxxx D
b0xxxxxxxxxxxxxxxxxxxxxxxxxxxxxxxx ^
#1620000
1#
#1680000
b1110 '
0#
